Workbook

Sheet README
A1: Supplementary Table S1 - Register of the review corpus (126 studies)
A2: Connecting Social Media Analysis and Financial Market Events: A Systematic Survey
A4: What this file is
A5: A study-level register of the 126 works included in the final synthesis. Each record is linked to its PRISMA category (Figure: PRISMA flow diagram), the manuscript section in which it is analysed and, where applicable, its methodological class (C1-C6, F1-F5) and appendix table.
A6: The register was compiled from the final manuscript and its bibliographic database on 18 October 2026 and synchronised with the revised manuscript on 19 October 2026 (all 146 cited keys: 126 in the corpus, 20 on not_in_corpus); bibliographic data are taken from surveybib_corrected.bib. Scripts and data files are described in the README.md of the accompanying repository.
A8: How the corpus was checked
A9: Every PRISMA category count is recomputed from the Data sheet (sheet PRISMA_check) and matches the flow diagram: social media analysis 59, financial market events 40, cross-domain events and causality 27 (total 126). Publication types are recomputed on the Counts sheet and match the corpus-composition table (103 journal articles, 7 conference papers, 3 books, 2 book chapters, 11 preprints/working papers).
A11: Metadata check
A12: On 19 October 2026 the bibliographic metadata of all 126 studies were checked against OpenAlex and their DOIs against Crossref (verify_corpus.py); corrections to the bibliographic database are listed on sheet bib_corrections.
A14: Retrospective known-item retrieval check (supplementary; sheets search_protocol, validation_result, validation_terms, protocol_history, openalex_fields)
A15: One protocol (search_protocol), following the objective approach of Hausner et al. (2012, Systematic Reviews 1:19). The 82 included studies published 2021-2026 were split at random within each flow-diagram category (seed 20261019) into a development set (44) and a validation set (38). Candidate terms were taken from the development titles only (words and two-word phrases in at least two titles) and from the keywords of Table 2; terms over-represented in the development titles relative to OpenAlex were kept, with the threshold chosen on the development set (R = 100), giving a title query of 27 terms (frozen, SHA-256 recorded). Restrictions: publication dates 2020-2026, ineligible document types excluded, OpenAlex subject fields of the development studies; no language restriction.
A16: Result (20 October 2026): 311,556 records (528,902 without the subject-field restriction on the same day; -41.1%); validation set 29 of 38 studies retrieved (76.3%, 95% CI 60.8-87.0%), 29 of the 36 indexed in OpenAlex (80.6%, 95% CI 65.0-90.2%); development set 42 of 44. The subject-field restriction was chosen after the fields of the validation studies had been inspected, so it is not independently validated; it did not remove any of the known included studies retrieved by the original query. The final configuration is used for the reported filtered retrieval result, while the original pre-specified configuration and all intermediate runs are retained as part of the methodological audit trail. The original configuration, a language filter that lost two studies without an assigned language, and rejected phrase-based variants are on sheet protocol_history. The check measures retrieval of known included studies; because both samples come from the included corpus, it cannot establish the completeness or sensitivity of the original search. Per-study results: Data, columns validation_set and retrieved_by_final_query.
... A19: Data - one row per included study. | not_in_corpus - 20 works cited in the manuscript only for background or methodological guidance. | codebook - definition of every column and label. | class_definitions - definitions of classes C1-C6 and F1-F5 quoted from the manuscript, with the assignment procedure and counts (formulas). | Counts - publication types, themes and classes (formulas). | PRISMA_check - diagram vs register (formulas). | search_concepts_table2 - search concepts and Boolean strings as reported in the manuscript. | search_protocol - protocol of the known-item retrieval check. | validation_result - filters, frozen query, threshold, records, retrieval in the development and validation sets, per-study result. | validation_terms - candidate terms with OpenAlex counts and over-representation ratios. | protocol_history - methodological audit trail: all configurations run (original pre-specified, intermediate, dropped, rejected and final), with records and retrieval; records by OpenAlex field. | openalex_fields - OpenAlex field, subfield and primary topic of the 82 studies published 2021-2026. | bib_corrections - corrections applied to surveybib.bib. | decisions_log - decisions taken when compiling the register.

Sheet Data
A1: study_id | B1: bibkey | C1: authors | D1: year | E1: title | F1: venue | G1: publication_type | H1: doi | I1: theme | J1: prisma_box | K1: xref_to | L1: section_no | M1: section | N1: method_class | O1: appendix_table | P1: cited_in | Q1: study_role | R1: revision_status | S1: metadata_check | T1: note | U1: openalex_id | V1: in_search_window | W1: validation_set | X1: retrieved_by_final_query
A2: S001 | B2: vandenbos2007apa | C2: VandenBos, Gary R. | D2: 2007 | E2: APA Dictionary of Psychology | F2: American Psychological Association | G2: Book | I2: Social media analysis | J2: Opinion in Social Networks | L2: 3.2 | M2: How Opinion Is Defined | P2: 3.2 How Opinion Is Defined | Q2: Foundational | S2: OpenAlex W1700102289 (matched by title); no DOI in .bib | U2: W1700102289 | V2: no
A3: S002 | B3: musch2003psychology | C3: Musch, Jochen; Klauer, Karl C | D3: 2003 | E3: The psychology of evaluation: Affective processes in cognition and emotion | F3: Psychology Press | G3: Book | I3: Social media analysis | J3: Opinion in Social Networks | L3: 3.2 | M3: How Opinion Is Defined | P3: 3.2 How Opinion Is Defined | Q3: Foundational | S3: Not indexed in OpenAlex | V3: no
A4: S003 | B4: zhang4450056integrated | C4: Zhang, Xiaoming John; Zhang, Ping | D4: 2023 | E4: An Integrated Mathematical Framework for Opinion Dynamics | F4: Available at SSRN | G4: Preprint / working paper | H4: 10.2139/ssrn.4450056 | I4: Social media analysis | J4: Opinion in Social Networks | L4: 3.2 | M4: How Opinion Is Defined | P4: 3.2 How Opinion Is Defined | Q4: Foundational | S4: OpenAlex W4376855031; Crossref DOI record checked | U4: W4376855031 | V4: yes | W4: development
A5: S004 | B5: degroot1974reaching | C5: DeGroot, Morris H | D5: 1974 | E5: Reaching a consensus | F5: Journal of the American Statistical association | G5: Journal article | H5: 10.1080/01621459.1974.10480137 | I5: Social media analysis | J5: Opinion in Social Networks | L5: 3.2 | M5: How Opinion Is Defined | P5: 3.2 How Opinion Is Defined | Q5: Foundational | S5: OpenAlex W1998692453; Crossref DOI record checked | U5: W1998692453 | V5: no
A6: S005 | B6: hegselmann2002opinion | C6: Hegselmann, Rainer; Krause, Ulrich | D6: 2002 | E6: Opinion dynamics and bounded confidence: models, analysis and simulation | F6: Journal of Artificial Societies and Social Simulation | G6: Journal article | I6: Social media analysis | J6: Opinion in Social Networks | L6: 3.2 | M6: How Opinion Is Defined | P6: 3.2 How Opinion Is Defined | Q6: Foundational | S6: OpenAlex W2113096089 (matched by title); no DOI in .bib | T6: Corrected in surveybib_corrected.bib (2026-10-19): journal: Typo in journal name | U6: W2113096089 | V6: no
A7: S006 | B7: friedkin1990social | C7: Friedkin, Noah E; Johnsen, Eugene C | D7: 1990 | E7: Social influence and opinions | F7: Journal of mathematical sociology | G7: Journal article | H7: 10.1080/0022250X.1990.9990069 | I7: Social media analysis | J7: Opinion in Social Networks | L7: 3.2 | M7: How Opinion Is Defined | P7: 3.2 How Opinion Is Defined | Q7: Foundational | S7: OpenAlex W2027514326; Crossref DOI record checked | U7: W2027514326 | V7: no
A8: S007 | B8: acemoglu2011opinion | C8: Acemoglu, Daron; Ozdaglar, Asuman | D8: 2011 | E8: Opinion dynamics and learning in social networks | F8: Dynamic Games and Applications | G8: Journal article | H8: 10.1007/s13235-010-0004-1 | I8: Social media analysis | J8: Opinion in Social Networks | L8: 3.2 | M8: How Opinion Is Defined | P8: 3.2 How Opinion Is Defined | Q8: Foundational | S8: OpenAlex W3122266916; Crossref DOI record checked | U8: W3122266916 | V8: no
A9: S008 | B9: gaillard2021countering | C9: Gaillard, Stefan; Oláh, Zoril A; Venmans, Stephan; Burke, Michael | D9: 2021 | E9: Countering the cognitive, linguistic, and psychological underpinnings behind susceptibility to fake news: A review of current literature with special focus on the role of age and digital literacy | F9: Frontiers in Communication | G9: Journal article | H9: 10.3389/fcomm.2021.661801 | I9: Social media analysis | J9: Opinion in Social Networks | L9: 3.2 | M9: How Opinion Is Defined | P9: 3.2 How Opinion Is Defined | Q9: Core | S9: OpenAlex W3182204087; Crossref DOI record checked | U9: W3182204087 | V9: yes | W9: validation | X9: yes
A10: S009 | B10: kietzmann2011social | C10: Kietzmann, Jan H; Hermkens, Kristopher; McCarthy, Ian P; Silvestre, Bruno S | D10: 2011 | E10: Social media? Get serious! Understanding the functional building blocks of social media | F10: Business horizons | G10: Journal article | H10: 10.1016/j.bushor.2011.01.005 | I10: Social media analysis | J10: Opinion in Social Networks | L10: 3.2 | M10: How Opinion Is Defined | P10: 3.2 How Opinion Is Defined | Q10: Foundational | S10: OpenAlex W2093425966; Crossref DOI record checked | U10: W2093425966 | V10: no
A11: S010 | B11: ienca2023artificial | C11: Ienca, Marcello | D11: 2023 | E11: On artificial intelligence and manipulation | F11: Topoi | G11: Journal article | H11: 10.1007/s11245-023-09940-3 | I11: Social media analysis | J11: Opinion Manipulation: Definition and Typologies | L11: 3.3 | M11: Opinion Manipulation and Typology | P11: 3.3 Opinion Manipulation and Typology | Q11: Core | S11: OpenAlex W4381430332 (matched by title); DOI corrected in .bib | T11: Corrected in surveybib_corrected.bib (2026-10-19): doi: DOI not registered in Crossref; DOI of the matching OpenAlex record | U11: W4381430332 | V11: yes | W11: validation | X11: yes
A12: S011 | B12: cayuela2025influence | C12: Cayuela Tudela, Alejandro David; Pastor-Galindo, Javier; Nespoli, Pantaleone; Ruipérez-Valiente, José A. | D12: 2025 | E12: The influence operation ontology (IOO) | F12: arXiv preprint arXiv:2503.07304 | G12: Preprint / working paper | H12: 10.48550/arXiv.2503.07304 | I12: Social media analysis | J12: Opinion Manipulation: Definition and Typologies | L12: 3.3 | M12: Opinion Manipulation and Typology | P12: 3.3 Opinion Manipulation and Typology | Q12: Core | S12: Not indexed in OpenAlex | T12: arXiv preprint; not indexed in OpenAlex. | V12: yes | W12: validation | X12: not indexed in OpenAlex
A13: S012 | B13: chang2022systematic | C13: Chang, Hao-Tien; Tsai, Fu-Ching | D13: 2022 | E13: A systematic review of Internet public opinion manipulation | F13: Procedia Computer Science | G13: Journal article | H13: 10.1016/j.procs.2022.09.373 | I13: Social media analysis | J13: Opinion Manipulation: Definition and Typologies | L13: 3.3 | M13: Opinion Manipulation and Typology | P13: 3.3 Opinion Manipulation and Typology | Q13: Core | S13: OpenAlex W4312651142 (matched by title); DOI corrected in .bib | T13: Corrected in surveybib_corrected.bib (2026-10-19): doi: DOI resolved to another article (A reverse personnel assignment method ...) | U13: W4312651142 | V13: yes | W13: development
A14: S013 | B14: pastor2025influence | C14: Pastor-Galindo, Javier; Nespoli, Pantaleone; Ruipérez-Valiente, José A; Camacho, David | D14: 2025 | E14: Influence operations in social networks | F14: arXiv preprint arXiv:2502.11827 | G14: Preprint / working paper | H14: 10.48550/arXiv.2502.11827 | I14: Social media analysis | J14: Opinion Manipulation: Definition and Typologies | L14: 3.3 | M14: Opinion Manipulation and Typology | P14: 3.3 Opinion Manipulation and Typology | Q14: Core | S14: OpenAlex W4407719590; arXiv DOI (registered with DataCite, not Crossref) | T14: Cited as arXiv preprint; OpenAlex lists a published version (IEEE Internet Computing, DOI 10.1109/MIC.2026.3700710). Optional update; would change publication-type counts. | U14: W4407719590 | V14: yes | W14: development
A15: S014 | B15: pal2025media | C15: Pal, Mayuree; Rashmi, CP | D15: 2025 | E15: Media Manipulation and Disinformation: The Role of AI in Fake News Creation and Its Impact on Trust in Media | F15: Digital Citizenship and Building a Responsible Online Presence | G15: Journal article | H15: 10.4018/979-8-3693-6675-2.ch013 | I15: Social media analysis | J15: Opinion Manipulation: Definition and Typologies | L15: 3.3 | M15: Opinion Manipulation and Typology | P15: 3.3 Opinion Manipulation and Typology | Q15: Core | S15: OpenAlex W4408684161; Crossref DOI record checked | T15: Book chapter recorded as @article in .bib. | U15: W4408684161 | V15: yes | W15: development
A16: S015 | B16: kumarsocial | C16: Kumar, Pramod | D16: 2025 | E16: Social Media Manipulation: A Strategic Tool in Contemporary Information Warfare | F16: New Man International Journal of Multidisciplinary Studies (NMIJMS) | G16: Journal article | I16: Social media analysis | J16: Opinion Manipulation: Definition and Typologies | L16: 3.3 | M16: Opinion Manipulation and Typology | P16: 3.3 Opinion Manipulation and Typology | Q16: Core | S16: Not indexed in OpenAlex | T16: Weak record: no volume, issue, pages or DOI; not indexed in OpenAlex. | V16: yes | W16: validation | X16: not indexed in OpenAlex
A17: S016 | B17: paul2023mathematical | C17: Paul, Arindam Kumar; Biswas, Md Haider Ali | D17: 2023 | E17: A Mathematical Theory for Studying and Controlling the Disinformation System Dynamics | F17: International Conference on Mathematical Analysis and Application in Modeling | G17: Conference paper | H17: 10.48550/arXiv.2401.05078 | I17: Social media analysis | J17: Class 1 - Mathematical and System-Dynamics Modelling | L17: 3.4 | M17: Opinion Detection and Modeling (C1) | N17: C1 | O17: Table C1 | P17: 3.4 Opinion Detection and Modeling; Appendix A.1 | Q17: Core | S17: OpenAlex W4407057928; arXiv DOI (registered with DataCite, not Crossref) | T17: Cited with the arXiv DOI; OpenAlex lists the published chapter (DOI 10.1007/978-981-97-9194-1_20). Optional update. | U17: W4407057928 | V17: yes | W17: development
A18: S017 | B18: ge2024novel | C18: Ge, Qing; Huang, Chen; Xu, Huiling; Zhang, Jun; Wang, Haixia | D18: 2024 | E18: A Novel SIR Model-Based Public Opinion Propagation and Optimal Control | F18: 2024 China Automation Congress (CAC) | G18: Conference paper | H18: 10.1109/CAC63892.2024.10865290 | I18: Social media analysis | J18: Class 1 - Mathematical and System-Dynamics Modelling | L18: 3.4 | M18: Opinion Detection and Modeling (C1) | N18: C1 | O18: Table C1 | P18: 3.4 Opinion Detection and Modeling; Appendix A.1 | Q18: Core | S18: OpenAlex W4407432899; Crossref DOI record checked | U18: W4407432899 | V18: yes | W18: development
A19: S018 | B19: evangelatos2025modeling | C19: Evangelatos, Spyridon; Veroni, Eleni; Efthymiou, Vasilis; Nikolopoulos, Christos | D19: 2025 | E19: Modeling disinformation spread in social networks: Phase transitions and mean-field analysis | F19: ACM Transactions on the Web | G19: Journal article | H19: 10.1145/3747287 | I19: Social media analysis | J19: Class 1 - Mathematical and System-Dynamics Modelling | L19: 3.4 | M19: Opinion Detection and Modeling (C1) | N19: C1 | O19: Table C1 | P19: 3.4 Opinion Detection and Modeling; Appendix A.1 | Q19: Core | S19: OpenAlex W4412593918; Crossref DOI record checked | U19: W4412593918 | V19: yes | W19: validation | X19: yes
A20: S019 | B20: zhou2020two | C20: Zhou, Qinyue; Wu, Zhibin; Altalhi, Abdulrahman H; Herrera, Francisco | D20: 2020 | E20: A two-step communication opinion dynamics model with self-persistence and influence index for social networks based on the degroot model | F20: Information Sciences | G20: Journal article | H20: 10.1016/j.ins.2020.01.052 | I20: Social media analysis | J20: Class 1 - Mathematical and System-Dynamics Modelling | L20: 3.4 | M20: Opinion Detection and Modeling (C1) | N20: C1 | O20: Table C1 | P20: 3.4 Opinion Detection and Modeling; Appendix A.1 | Q20: Core | S20: OpenAlex W3004050991 (matched by title); DOI corrected in .bib | T20: Corrected in surveybib_corrected.bib (2026-10-19): doi: DOI resolved to another article (Recognizing novel patterns via adversarial learning ...) | U20: W3004050991 | V20: no
A21: S020 | B21: butts2023mathematical | C21: Butts, David J; Bollman, Sam A; Murillo, Michael S | D21: 2023 | E21: Mathematical modeling of disinformation and effectiveness of mitigation policies | F21: Scientific Reports | G21: Journal article | H21: 10.1038/s41598-023-45710-2 | I21: Social media analysis | J21: Class 1 - Mathematical and System-Dynamics Modelling | L21: 3.4 | M21: Opinion Detection and Modeling (C1) | N21: C1 | O21: Table C1 | P21: 3.4 Opinion Detection and Modeling; Appendix A.1 | Q21: Core | S21: OpenAlex W4388048121 (matched by title); DOI corrected in .bib | T21: Corrected in surveybib_corrected.bib (2026-10-19): doi: DOI not registered in Crossref; DOI of the matching OpenAlex record | U21: W4388048121 | V21: yes | W21: development
A22: S021 | B22: bhalla2025local | C22: Bhalla, Nikita; Lechowicz, Adam; Musco, Cameron | D22: 2025 | E22: Local edge dynamics and opinion polarization | F22: ACM Transactions on Intelligent Systems and Technology | G22: Journal article | H22: 10.1145/3709006 | I22: Social media analysis | J22: Class 1 - Mathematical and System-Dynamics Modelling | L22: 3.4 | M22: Opinion Detection and Modeling (C1) | N22: C1 | O22: Table C1 | P22: 3.4 Opinion Detection and Modeling; Appendix A.1 | Q22: Core | S22: OpenAlex W3216173699; Crossref DOI record checked | U22: W3216173699 | V22: yes | W22: validation | X22: yes
A23: S022 | B23: mridha2021comprehensive | C23: Mridha, Muhammad Firoz; Keya, Ashfia Jannat; Hamid, Md Abdul; Monowar, Muhammad Mostafa; Rahman, Md Saifur | D23: 2021 | E23: A comprehensive review on fake news detection with deep learning | F23: IEEE access | G23: Journal article | H23: 10.1109/ACCESS.2021.3129329 | I23: Social media analysis | J23: Class 2 - Machine & Deep Learning Content Detection | L23: 3.4 | M23: Opinion Detection and Modeling (C2) | N23: C2 | O23: Table C2 | P23: 3.4 Opinion Detection and Modeling; Appendix A.1 | Q23: Core | S23: OpenAlex W3216370178 (matched by title); DOI corrected in .bib | T23: Corrected in surveybib_corrected.bib (2026-10-19): doi: DOI resolved to another article (Incremental Attribute Reduction ...) | U23: W3216370178 | V23: yes | W23: validation | X23: yes
A24: S023 | B24: saadi2025enhancing | C24: Saadi, Abdelhalim; Belhadef, Hacene; Guessas, Akram; Hafirassou, Oussama | D24: 2025 | E24: Enhancing Fake News Detection with Transformer Models and Summarization | F24: Engineering, Technology & Applied Science Research | G24: Journal article | H24: 10.48084/etasr.10678 | I24: Social media analysis | J24: Class 2 - Machine & Deep Learning Content Detection | L24: 3.4 | M24: Opinion Detection and Modeling (C2) | N24: C2 | O24: Table C2 | P24: 3.4 Opinion Detection and Modeling; Appendix A.1 | Q24: Core | S24: OpenAlex W4411122931; Crossref DOI record checked | U24: W4411122931 | V24: yes | W24: validation | X24: yes
A25: S024 | B25: huang2025hybrid | C25: Huang, Tianyi; Xu, Zeqiu; Yu, Peiyang; Yi, Jingyuan; Xu, Xiaochuan | D25: 2025 | E25: A hybrid transformer model for fake news detection: Leveraging Bayesian optimization and bidirectional recurrent unit | F25: arXiv preprint arXiv:2502.09097 | G25: Preprint / working paper | H25: 10.1109/ISBDAS64762.2025.11117058 | I25: Social media analysis | J25: Class 2 - Machine & Deep Learning Content Detection | L25: 3.4 | M25: Opinion Detection and Modeling (C2) | N25: C2 | O25: Table C2 | P25: 3.4 Opinion Detection and Modeling; Appendix A.1 | Q25: Core | S25: OpenAlex W4413394554; Crossref DOI record checked | T25: Recorded as arXiv preprint; DOI is the published IEEE conference version. | U25: W4413394554 | V25: yes | W25: validation | X25: yes
A26: S025 | B26: tufchi2024transvae | C26: Tufchi, Shivani; Ahmed, Tanveer; Yadav, Ashima; Agrawal, Krishna Kant; Vidyarthi, Ankit | D26: 2024 | E26: TransVAE-PAM: A combined transformer and DAG-based approach for enhanced fake news detection in the Indian context | F26: ACM Transactions on Asian and Low-Resource Language Information Processing | G26: Journal article | H26: 10.1145/3651160 | I26: Social media analysis | J26: Class 2 - Machine & Deep Learning Content Detection | L26: 3.4 | M26: Opinion Detection and Modeling (C2) | N26: C2 | O26: Table C2 | P26: 3.4 Opinion Detection and Modeling; Appendix A.1 | Q26: Core | S26: OpenAlex W4392347598; Crossref DOI record checked | U26: W4392347598 | V26: yes | W26: development
A27: S026 | B27: sharma2025novel | C27: Sharma, Prateema; Al-Dayyeni, Wisam; Nagpal, Tapsi; Rana, Arun; Purohit, Rahul; Elaraby, Ahmed | D27: 2025 | E27: A Novel Hybrid Algorithm for Fake News Detection | F27: Digital Threats: Research and Practice | G27: Journal article | H27: 10.1145/3728473 | I27: Social media analysis | J27: Class 2 - Machine & Deep Learning Content Detection | L27: 3.4 | M27: Opinion Detection and Modeling (C2) | N27: C2 | O27: Table C2 | P27: 3.4 Opinion Detection and Modeling; Appendix A.1 | Q27: Core | S27: OpenAlex W4409256702; Crossref DOI record checked | U27: W4409256702 | V27: yes | W27: validation | X27: yes
A28: S027 | B28: ozcelik2025detecting | C28: Ozcelik, Oguzhan; Toraman, Cagri; Can, Fazli | D28: 2025 | E28: Detecting misinformation on social media using community insights and contrastive learning | F28: ACM Transactions on Intelligent Systems and Technology | G28: Journal article | H28: 10.1145/3709009 | I28: Social media analysis | J28: Class 2 - Machine & Deep Learning Content Detection | L28: 3.4 | M28: Opinion Detection and Modeling (C2) | N28: C2 | O28: Table C2 | P28: 3.4 Opinion Detection and Modeling; Appendix A.1 | Q28: Core | S28: OpenAlex W4405566696; Crossref DOI record checked | U28: W4405566696 | V28: yes | W28: development
A29: S028 | B29: yang2025llm | C29: Yang, Ruichao; Ma, Jing; Gao, Wei; Lin, Hongzhan | D29: 2025 | E29: LLM-enhanced multiple instance learning for joint rumor and stance detection with social context information | F29: ACM Transactions on Intelligent Systems and Technology | G29: Journal article | H29: 10.1145/3716856 | I29: Social media analysis | J29: Class 2 - Machine & Deep Learning Content Detection | L29: 3.4 | M29: Opinion Detection and Modeling (C2) | N29: C2 | O29: Table C2 | P29: 3.4 Opinion Detection and Modeling; Appendix A.1 | Q29: Core | S29: OpenAlex W4407369317; Crossref DOI record checked | U29: W4407369317 | V29: yes | W29: development
A30: S029 | B30: mahmud2026detecting | C30: Mahmud, Tanjim; Rahman, Md Akash; Devnath, Rimon Kanthi; Hossain, Mohammad Shahadat; Andersson, Karl | D30: 2026 | E30: Detecting Fake News in Bangla Using Linguistic and Psychological Features | F30: ACM Transactions on Social Computing | G30: Journal article | H30: 10.1145/3798302 | I30: Social media analysis | J30: Class 2 - Machine & Deep Learning Content Detection | L30: 3.4 | M30: Opinion Detection and Modeling (C2) | N30: C2 | O30: Table C2 | P30: 3.4 Opinion Detection and Modeling; Appendix A.1 | Q30: Core | S30: OpenAlex W7130827924; Crossref DOI record checked | U30: W7130827924 | V30: yes | W30: development
A31: S030 | B31: sahitaj2025hybrid | C31: Sahitaj, Ariana; Sahitaj, Premtim; Solopova, Veronika; Li, Jiaao; Möller, Sebastian; Schmitt, Vera | D31: 2025 | E31: Hybrid Annotation for Propaganda Detection: Integrating LLM Pre-Annotations with Human Intelligence | F31: arXiv preprint arXiv:2507.18343 | G31: Preprint / working paper | H31: 10.18653/v1/2025.nlp4pi-1.18 | I31: Social media analysis | J31: Class 3 - Hybrid Human-AI Annotation and Verification | L31: 3.4 | M31: Opinion Detection and Modeling (C3) | N31: C3 | O31: Table C3 | P31: 3.4 Opinion Detection and Modeling; Appendix A.1 | Q31: Core | S31: OpenAlex W4412944267; Crossref DOI record checked | T31: Recorded as arXiv preprint; DOI is the published workshop version. | U31: W4412944267 | V31: yes | W31: development
A32: S031 | B32: fan2026skeptik | C32: Fan, Arlen; Lei, Fan; Corman, Steven R; Maciejewski, Ross | D32: 2026 | E32: Skeptik: A Hybrid Framework for Combating Potential Misinformation in Journalism | F32: ACM Transactions on Interactive Intelligent Systems | G32: Journal article | H32: 10.1145/3766891 | I32: Social media analysis | J32: Class 3 - Hybrid Human-AI Annotation and Verification | L32: 3.4 | M32: Opinion Detection and Modeling (C3) | N32: C3 | O32: Table C3 | P32: 3.4 Opinion Detection and Modeling; Appendix A.1 | Q32: Core | S32: OpenAlex W4414476222; Crossref DOI record checked | U32: W4414476222 | V32: yes | W32: development
A33: S032 | B33: liu2024exploring | C33: Liu, Houjiang; Gwizdka, Jacek; Lease, Matthew | D33: 2024 | E33: Exploring Multidimensional Checkworthiness: Designing AI-assisted Claim Prioritization for Human Fact-checkers | F33: arXiv preprint arXiv:2412.08185 | G33: Preprint / working paper | H33: 10.1145/3757473 | I33: Social media analysis | J33: Class 3 - Hybrid Human-AI Annotation and Verification | L33: 3.4 | M33: Opinion Detection and Modeling (C3) | N33: C3 | O33: Table C3 | P33: 3.4 Opinion Detection and Modeling; Appendix A.1 | Q33: Core | S33: OpenAlex W4415256754; Crossref DOI record checked | T33: Recorded as arXiv preprint; DOI is the published ACM version. | U33: W4415256754 | V33: yes | W33: validation | X33: no
A34: S033 | B34: hrckova2025autonomation | C34: Hrckova, Andrea; Moro, Robert; Srba, Ivan; Simko, Jakub; Bielikova, Maria | D34: 2025 | E34: Autonomation, Not Automation: Activities and Needs of European Fact-checkers as a Basis for Designing Human-centered AI Systems | F34: ACM Journal on Responsible Computing | G34: Journal article | H34: 10.1145/3764592 | I34: Social media analysis | J34: Class 3 - Hybrid Human-AI Annotation and Verification | L34: 3.4 | M34: Opinion Detection and Modeling (C3) | N34: C3 | O34: Table C3 | P34: 3.4 Opinion Detection and Modeling; Appendix A.1 | Q34: Core | S34: OpenAlex W4414032582; Crossref DOI record checked | U34: W4414032582 | V34: yes | W34: validation | X34: no
A35: S034 | B35: cui2025toward | C35: Cui, Zikun; Huang, Tianyi; Chiang, Chia-En; Du, Cuiqianhe | D35: 2025 | E35: Toward Verifiable Misinformation Detection: A Multi-Tool LLM Agent Framework | F35: arXiv preprint arXiv:2508.03092 | G35: Preprint / working paper | H35: 10.1145/3766918.3766948 | I35: Social media analysis | J35: Class 3 - Hybrid Human-AI Annotation and Verification | L35: 3.4 | M35: Opinion Detection and Modeling (C3) | N35: C3 | O35: Table C3 | P35: 3.4 Opinion Detection and Modeling; Appendix A.1 | Q35: Core | S35: OpenAlex W4415736465; Crossref DOI record checked | T35: Recorded as arXiv preprint; DOI is the published ACM version. | U35: W4415736465 | V35: yes | W35: validation | X35: yes
A36: S035 | B36: lee2025countering | C36: Lee, Tuan-He; Fussell, Susan R | D36: 2025 | E36: Countering misinformation in private messaging groups: Insights from a fact-checking chatbot | F36: Proceedings of the ACM on human-computer interaction | G36: Journal article | H36: 10.1145/3701189 | I36: Social media analysis | J36: Class 3 - Hybrid Human-AI Annotation and Verification | L36: 3.4 | M36: Opinion Detection and Modeling (C3) | N36: C3 | O36: Table C3 | P36: 3.4 Opinion Detection and Modeling; Appendix A.1 | Q36: Core | S36: OpenAlex W4406258040; Crossref DOI record checked | U36: W4406258040 | V36: yes | W36: development
A37: S036 | B37: nobre2022hierarchical | C37: Nobre, Gabriel Peres; Ferreira, Carlos HG; Almeida, Jussara M | D37: 2022 | E37: A hierarchical network-oriented analysis of user participation in misinformation spread on WhatsApp | F37: Information Processing & Management | G37: Journal article | H37: 10.1016/j.ipm.2021.102757 | I37: Social media analysis | J37: Class 4 - Network Structure and Propagation Analysis | L37: 3.4 | M37: Opinion Detection and Modeling (C4) | N37: C4 | O37: Table C4 | P37: 3.4 Opinion Detection and Modeling; 4.1.3 Event-Level Descriptors; Appendix A.1 | Q37: Core | S37: OpenAlex W3203440807; Crossref DOI record checked | U37: W3203440807 | V37: yes | W37: validation | X37: yes
A38: S037 | B38: resende2019analyzing | C38: Resende, Gustavo; Melo, Philipe; CS Reis, Julio; Vasconcelos, Marisa; Almeida, Jussara M; Benevenuto, Fabrício | D38: 2019 | E38: Analyzing textual (mis) information shared in WhatsApp groups | F38: Proceedings of the 10th ACM Conference on Web Science | G38: Conference paper | H38: 10.1145/3292522.3326029 | I38: Social media analysis | J38: Class 4 - Network Structure and Propagation Analysis | L38: 3.4 | M38: Opinion Detection and Modeling (C4) | N38: C4 | O38: Table C4 | P38: 3.4 Opinion Detection and Modeling; 4.1.3 Event-Level Descriptors; Appendix A.1 | Q38: Core | S38: OpenAlex W2954093511; Crossref DOI record checked | U38: W2954093511 | V38: no
A39: S038 | B39: chen2022social | C39: Chen, Long; Chen, Jianguo; Xia, Chunhe | D39: 2022 | E39: Social network behavior and public opinion manipulation | F39: Journal of Information Security and Applications | G39: Journal article | H39: 10.1016/j.jisa.2021.103060 | I39: Social media analysis | J39: Class 4 - Network Structure and Propagation Analysis | L39: 3.4 | M39: Opinion Detection and Modeling (C4) | N39: C4 | O39: Table C4 | P39: 3.4 Opinion Detection and Modeling; Appendix A.1 | Q39: Core | S39: OpenAlex W4200463617; Crossref DOI record checked | U39: W4200463617 | V39: yes | W39: validation | X39: yes
A40: S039 | B40: loru2026compression | C40: Loru, Edoardo; Di Marco, Niccolò; Cinelli, Matteo; Quattrociocchi, Walter | D40: 2026 | E40: A Compression-Based Approach to Detecting Automated and Coordinated Behavior on Social Media | F40: ACM Transactions on Knowledge Discovery from Data | G40: Journal article | H40: 10.1145/3778356 | I40: Social media analysis | J40: Class 4 - Network Structure and Propagation Analysis | L40: 3.4 | M40: Opinion Detection and Modeling (C4) | N40: C4 | O40: Table C4 | P40: 3.4 Opinion Detection and Modeling; Appendix A.1 | Q40: Core | S40: OpenAlex W4416841974; Crossref DOI record checked | U40: W4416841974 | V40: yes | W40: development
A41: S040 | B41: bellina2025language | C41: Bellina, Alessandro; Sardo, Donald Ruggiero Lo; Brugnoli, Emanuele; Saracco, Fabio; Gravino, Pietro; Loreto, Vittorio; Di Bona, Gabriele | D41: 2025 | E41: Language bubbles in online social networks | F41: arXiv preprint arXiv:2507.13068 | G41: Preprint / working paper | H41: 10.48550/arXiv.2507.13068 | I41: Social media analysis | J41: Class 4 - Network Structure and Propagation Analysis | L41: 3.4 | M41: Opinion Detection and Modeling (C4) | N41: C4 | O41: Table C4 | P41: 3.4 Opinion Detection and Modeling; Appendix A.1 | Q41: Core | S41: OpenAlex W4415310342; arXiv DOI (registered with DataCite, not Crossref) | U41: W4415310342 | V41: yes | W41: development
A42: S041 | B42: impicciche2025comparing | C42: Impiccichè, Paola; Viviani, Marco | D42: 2025 | E42: Comparing echo chamber detection metrics: A cross-modeling and cross-platform analysis of Twitter and Reddit | F42: ACM Transactions on the Web | G42: Journal article | H42: 10.1145/3707701 | I42: Social media analysis | J42: Class 4 - Network Structure and Propagation Analysis | L42: 3.4 | M42: Opinion Detection and Modeling (C4) | N42: C4 | O42: Table C4 | P42: 3.4 Opinion Detection and Modeling; Appendix A.1 | Q42: Core | S42: OpenAlex W4405248842; Crossref DOI record checked | U42: W4405248842 | V42: yes | W42: development
A43: S042 | B43: wang2026rumor | C43: Wang, R.; Lv, N.; Wang, L.; Li, Q.; Duan, S.; Xiao, Y. | D43: 2026 | E43: A Rumor Propagation Prediction Based on Multi-dimensional User Characteristics | F43: ACM Transactions on Internet Technology | G43: Journal article | H43: 10.1145/3795885 | I43: Social media analysis | J43: Class 4 - Network Structure and Propagation Analysis | L43: 3.4 | M43: Opinion Detection and Modeling (C4) | N43: C4 | O43: Table C4 | P43: 3.4 Opinion Detection and Modeling; Appendix A.1 | Q43: Core | S43: OpenAlex W7131085584; Crossref DOI record checked | T43: Volume/issue/pages in .bib look copied from another entry; verify. | U43: W7131085584 | V43: yes | W43: development
A44: S043 | B44: fawzi2024pinocchio | C44: Fawzi, Mahmoud; Magdy, Walid | D44: 2024 | E44: "Pinocchio had a Nose, You have a Network!": On Characterizing Fake News Spreaders on Arabic Social Media | F44: Proceedings of the ACM on Human-Computer Interaction | G44: Journal article | H44: 10.1145/3653702 | I44: Social media analysis | J44: Class 4 - Network Structure and Propagation Analysis | L44: 3.4 | M44: Opinion Detection and Modeling (C4) | N44: C4 | O44: Table C4 | P44: 3.4 Opinion Detection and Modeling; Appendix A.1 | Q44: Core | S44: OpenAlex W4396218575; Crossref DOI record checked | U44: W4396218575 | V44: yes | W44: validation | X44: yes
A45: S044 | B45: escola2023falls | C45: Escolà-Gascón, Álex; Dagnall, Neil; Denovan, Andrew; Drinkwater, Kenneth; Diez-Bosch, Miriam | D45: 2023 | E45: Who falls for fake news? Psychological and clinical profiling evidence of fake news consumers | F45: Personality and individual differences | G45: Journal article | H45: 10.1016/j.paid.2022.111893 | I45: Social media analysis | J45: Class 5 - Behavioural and Psychological Modelling | L45: 3.4 | M45: Opinion Detection and Modeling (C5) | N45: C5 | O45: Table C5 | P45: 3.4 Opinion Detection and Modeling; Appendix A.1 | Q45: Core | S45: OpenAlex W4294883912; Crossref DOI record checked | U45: W4294883912 | V45: yes | W45: validation | X45: yes
A46: S045 | B46: smith2024unraveling | C46: Smith, Troy | D46: 2024 | E46: Unraveling the digital emotion web: exploring the relationship between online emotional expression, perception, management, psychopathologies, and social media use | F46: Current Psychology | G46: Journal article | H46: 10.1007/s12144-023-05350-1 | I46: Social media analysis | J46: Class 5 - Behavioural and Psychological Modelling | L46: 3.4 | M46: Opinion Detection and Modeling (C5) | N46: C5 | O46: Table C5 | P46: 3.4 Opinion Detection and Modeling; Appendix A.1 | Q46: Core | S46: OpenAlex W4388084625 (matched by title); DOI corrected in .bib | T46: Corrected in surveybib_corrected.bib (2026-10-19): doi: DOI not registered in Crossref; DOI of the matching OpenAlex record | U46: W4388084625 | V46: yes | W46: validation | X46: no
A47: S046 | B47: lutz2024linguistic | C47: Lutz, Bernhard; Adam, Marc; Feuerriegel, Stefan; Pröllochs, Nicolas; Neumann, Dirk | D47: 2024 | E47: Which linguistic cues make people fall for fake news? A comparison of cognitive and affective processing | F47: Proceedings of the ACM on human-Computer Interaction | G47: Journal article | H47: 10.1145/3641030 | I47: Social media analysis | J47: Class 5 - Behavioural and Psychological Modelling | L47: 3.4 | M47: Opinion Detection and Modeling (C5) | N47: C5 | O47: Table C5 | P47: 3.4 Opinion Detection and Modeling; Appendix A.1 | Q47: Core | S47: OpenAlex W4396218134; Crossref DOI record checked | U47: W4396218134 | V47: yes | W47: development
A48: S047 | B48: sakib2025understanding | C48: Sakib, Mostofa Najmus; Ahmed, Md Shoaib; Spezzano, Francesca; Hamby, Anne | D48: 2025 | E48: Understanding News Consumers' Perceptions of Believability: A Study of Real and Fake News | F48: Proceedings of the ACM on Human-Computer Interaction | G48: Journal article | H48: 10.1145/3757691 | I48: Social media analysis | J48: Class 5 - Behavioural and Psychological Modelling | L48: 3.4 | M48: Opinion Detection and Modeling (C5) | N48: C5 | O48: Table C5 | P48: 3.4 Opinion Detection and Modeling; Appendix A.1 | Q48: Core | S48: OpenAlex W4415258878; Crossref DOI record checked | U48: W4415258878 | V48: yes | W48: validation | X48: yes
A49: S048 | B49: amieur2025comparative | C49: Amieur, Nardjes; Chouaki, Salim; Goga, Oana; Roussillon, Beatrice | D49: 2025 | E49: A comparative study of news exposure and consumption on and off Facebook | F49: Proceedings of the ACM on Human-Computer Interaction | G49: Journal article | H49: 10.1145/3757540 | I49: Social media analysis | J49: Class 5 - Behavioural and Psychological Modelling | L49: 3.4 | M49: Opinion Detection and Modeling (C5) | N49: C5 | O49: Table C5 | P49: 3.4 Opinion Detection and Modeling; Appendix A.1 | Q49: Core | S49: OpenAlex W4415250186; Crossref DOI record checked | U49: W4415250186 | V49: yes | W49: validation | X49: yes
A50: S049 | B50: budak2024misunderstanding | C50: Budak, Ceren; Nyhan, Brendan; Rothschild, David M; Thorson, Emily; Watts, Duncan J | D50: 2024 | E50: Misunderstanding the harms of online misinformation | F50: Nature | G50: Journal article | H50: 10.1038/s41586-024-07417-w | I50: Social media analysis | J50: Class 5 - Behavioural and Psychological Modelling | L50: 3.4 | M50: Opinion Detection and Modeling (C5) | N50: C5 | O50: Table C5 | P50: 3.4 Opinion Detection and Modeling; Appendix A.1 | Q50: Core | S50: OpenAlex W4399366359 (matched by title); DOI corrected in .bib | T50: Corrected in surveybib_corrected.bib (2026-10-19): doi: DOI not registered in Crossref; DOI of the matching OpenAlex record | U50: W4399366359 | V50: yes | W50: development
A51: S050 | B51: khan2024targets | C51: Khan, Sadia O; Ghafourian, Tania; Patil, Sameer | D51: 2024 | E51: Targets of weaponized islamophobia: The impact of misinformation on the online practices of Muslims in the United States | F51: Proceedings of the ACM on human-computer interaction | G51: Journal article | H51: 10.1145/3637403 | I51: Social media analysis | J51: Class 5 - Behavioural and Psychological Modelling | L51: 3.4 | M51: Opinion Detection and Modeling (C5) | N51: C5 | O51: Table C5 | P51: 3.4 Opinion Detection and Modeling; Appendix A.1 | Q51: Core | S51: OpenAlex W4396218543; Crossref DOI record checked | U51: W4396218543 | V51: yes | W51: development
A52: S051 | B52: govers2025feeds | C52: Govers, Jarod; Pareek, Saumya; Velloso, Eduardo; Goncalves, Jorge | D52: 2025 | E52: Feeds of distrust: Investigating how AI-powered news chatbots shape user trust and perceptions | F52: ACM Transactions on Interactive Intelligent Systems | G52: Journal article | H52: 10.1145/3722227 | I52: Social media analysis | J52: Class 5 - Behavioural and Psychological Modelling | L52: 3.4 | M52: Opinion Detection and Modeling (C5) | N52: C5 | O52: Table C5 | P52: 3.4 Opinion Detection and Modeling; Appendix A.1 | Q52: Core | S52: OpenAlex W4408449869; Crossref DOI record checked | U52: W4408449869 | V52: yes | W52: development
A53: S052 | B53: roozenbeek2022technique | C53: Roozenbeek, Jon; Traberg, Cecilie S; van der Linden, Sander | D53: 2022 | E53: Technique-based inoculation against real-world misinformation | F53: Royal Society open science | G53: Journal article | H53: 10.1098/rsos.211719 | I53: Social media analysis | J53: Class 6 - Intervention and Inoculation Strategies | L53: 3.4 | M53: Opinion Detection and Modeling (C6) | N53: C6 | O53: Table C6 | P53: 3.4 Opinion Detection and Modeling; Appendix A.1 | Q53: Core | S53: OpenAlex W4280610708; Crossref DOI record checked | U53: W4280610708 | V53: yes | W53: validation | X53: yes
A54: S053 | B54: wang2025limited | C54: Wang, Sze Yuh Nina; Phillips, Samantha C; Carley, Kathleen M; Lin, Hause; Pennycook, Gordon | D54: 2025 | E54: Limited effectiveness of psychological inoculation against misinformation in a social media feed | F54: PNAS nexus | G54: Journal article | H54: 10.1093/pnasnexus/pgaf172 | I54: Social media analysis | J54: Class 6 - Intervention and Inoculation Strategies | L54: 3.4 | M54: Opinion Detection and Modeling (C6) | N54: C6 | O54: Table C6 | P54: 3.4 Opinion Detection and Modeling; Appendix A.1 | Q54: Core | S54: OpenAlex W4410833287; Crossref DOI record checked | U54: W4410833287 | V54: yes | W54: validation | X54: yes
A55: S054 | B55: tang2025breaking | C55: Tang, Huiyun; Sun, Songqi; Nie, Kexin; Li, Ang; Sergeeva, Anastasia; Lc, Ray | D55: 2025 | E55: Breaking the News: Taking the Roles of Influencer vs. Journalist in a LLM-Based Game for Raising Misinformation Awareness | F55: Proceedings of the ACM on Human-Computer Interaction | G55: Journal article | H55: 10.1145/3748600 | I55: Social media analysis | J55: Class 6 - Intervention and Inoculation Strategies | L55: 3.4 | M55: Opinion Detection and Modeling (C6) | N55: C6 | O55: Table C6 | P55: 3.4 Opinion Detection and Modeling; Appendix A.1 | Q55: Core | S55: OpenAlex W4414836461; Crossref DOI record checked | U55: W4414836461 | V55: yes | W55: development
A56: S055 | B56: chuai2024did | C56: Chuai, Yuwei; Tian, Haoye; Pröllochs, Nicolas; Lenzini, Gabriele | D56: 2024 | E56: Did the roll-out of Community Notes reduce engagement with misinformation on X/Twitter? | F56: Proceedings of the ACM on human-computer interaction | G56: Journal article | H56: 10.1145/3686967 | I56: Social media analysis | J56: Class 6 - Intervention and Inoculation Strategies | K56: Causal Identification | L56: 3.4 | M56: Opinion Detection and Modeling (C6) | N56: C6 | O56: Table C6 | P56: 3.4 Opinion Detection and Modeling; 4.2.1 Causal Identification in Cross-Domain Research; Appendix A.1 | Q56: Core | S56: OpenAlex W4404171602; Crossref DOI record checked | U56: W4404171602 | V56: yes | W56: development
A57: S056 | B57: jeon2024hearhere | C57: Jeon, Youngseung; Kim, Jaehoon; Park, Sohyun; Ko, Yunyong; Ryu, Seongeun; Kim, Sang-Wook; Han, Kyungsik | D57: 2024 | E57: HearHere: Mitigating echo chambers in news consumption through an AI-based web system | F57: Proceedings of the ACM on Human-Computer Interaction | G57: Journal article | H57: 10.1145/3637340 | I57: Social media analysis | J57: Class 6 - Intervention and Inoculation Strategies | L57: 3.4 | M57: Opinion Detection and Modeling (C6) | N57: C6 | O57: Table C6 | P57: 3.4 Opinion Detection and Modeling; Appendix A.1 | Q57: Core | S57: OpenAlex W4396230918; Crossref DOI record checked | U57: W4396230918 | V57: yes | W57: validation | X57: yes
A58: S057 | B58: yu2025breaking | C58: Yu, Dianer; Li, Qian; Huo, Huan; Xu, Guandong | D58: 2025 | E58: Breaking the Loop: Causal Learning to Mitigate Echo Chambers in Social Networks | F58: ACM Transactions on Information Systems | G58: Journal article | H58: 10.1145/3757738 | I58: Social media analysis | J58: Class 6 - Intervention and Inoculation Strategies | L58: 3.4 | M58: Opinion Detection and Modeling (C6) | N58: C6 | O58: Table C6 | P58: 3.4 Opinion Detection and Modeling; Appendix A.1 | Q58: Core | S58: OpenAlex W4412827327; Crossref DOI record checked | U58: W4412827327 | V58: yes | W58: development
A59: S058 | B59: su2025emotionally | C59: Su, Xiaotian; Zierau, Naim; Kim, Soomin; Wang, April Yi; Wambsganss, Thiemo | D59: 2025 | E59: Emotionally Aware Moderation: The Potential of Emotion Monitoring in Shaping Healthier Social Media Conversations | F59: Proceedings of the ACM on Human-Computer Interaction | G59: Journal article | H59: 10.1145/3757472 | I59: Social media analysis | J59: Class 6 - Intervention and Inoculation Strategies | L59: 3.4 | M59: Opinion Detection and Modeling (C6) | N59: C6 | O59: Table C6 | P59: 3.4 Opinion Detection and Modeling; Appendix A.1 | Q59: Core | S59: OpenAlex W4415256889; Crossref DOI record checked | U59: W4415256889 | V59: yes | W59: validation | X59: no
A60: S059 | B60: shahid2025one | C60: Shahid, Farhana; Agarwal, Dhruv; Vashistha, Aditya | D60: 2025 | E60: One style does not regulate all: Moderation practices in public and private WhatsApp groups | F60: Proceedings of the ACM on Human-Computer Interaction | G60: Journal article | H60: 10.1145/3711042 | I60: Social media analysis | J60: Class 6 - Intervention and Inoculation Strategies | L60: 3.4 | M60: Opinion Detection and Modeling (C6) | N60: C6 | O60: Table C6 | P60: 3.4 Opinion Detection and Modeling; Appendix A.1 | Q60: Core | S60: OpenAlex W4410049549; Crossref DOI record checked | U60: W4410049549 | V60: yes | W60: development
A61: S060 | B61: mackinlay1997event | C61: MacKinlay, A Craig | D61: 1997 | E61: Event studies in economics and finance | F61: Journal of economic literature | G61: Journal article | H61: 10.1257/jel.35.1.13 | I61: Financial market events | J61: F1 - Classical event-study econometrics | K61: Causal Identification | L61: 3.6 | M61: Methodological Approaches in Financial Event Research (F1) | N61: F1 | O61: Table F1 | P61: 3.6 Methodological Approaches in Financial Event Research; 4.1.3 Event-Level Descriptors; 4.2.1 Causal Identification in Cross-Domain Research; Appendix A.1 | Q61: Foundational | S61: OpenAlex W2130162792; DOI not registered in Crossref | T61: DOI 10.1257/jel.35.1.13 is not registered in Crossref; verify or replace with the JSTOR stable URL. | U61: W2130162792 | V61: no
A62: S061 | B62: el2023event | C62: El Ghoul, Sadok; Guedhami, Omrane; Mansi, Sattar A; Sy, Oumar | D62: 2023 | E62: Event studies in international finance research | F62: Journal of international business studies | G62: Journal article | H62: 10.1057/s41267-022-00534-6 | I62: Financial market events | J62: F1 - Classical event-study econometrics | L62: 3.6 | M62: Methodological Approaches in Financial Event Research (F1) | N62: F1 | O62: Table F1 | P62: 3.6 Methodological Approaches in Financial Event Research; Appendix A.1 | Q62: Foundational | S62: OpenAlex W4284883529; Crossref DOI record checked | U62: W4284883529 | V62: yes | W62: development
A63: S062 | B63: corrado1989nonparametric | C63: Corrado, Charles J | D63: 1989 | E63: A nonparametric test for abnormal security-price performance in event studies | F63: Journal of financial economics | G63: Journal article | H63: 10.1016/0304-405X(89)90064-0 | I63: Financial market events | J63: F1 - Classical event-study econometrics | L63: 3.6 | M63: Methodological Approaches in Financial Event Research (F1) | N63: F1 | O63: Table F1 | P63: 3.6 Methodological Approaches in Financial Event Research; Appendix A.1 | Q63: Foundational | S63: OpenAlex W2028513078; Crossref DOI record checked | U63: W2028513078 | V63: no
A64: S063 | B64: boehmer1991event | C64: Boehmer, Ekkehart; Masumeci, Jim; Poulsen, Annette B | D64: 1991 | E64: Event-study methodology under conditions of event-induced variance | F64: Journal of financial economics | G64: Journal article | H64: 10.1016/0304-405X(91)90032-F | I64: Financial market events | J64: F1 - Classical event-study econometrics | L64: 3.6 | M64: Methodological Approaches in Financial Event Research (F1) | N64: F1 | O64: Table F1 | P64: 3.6 Methodological Approaches in Financial Event Research; Appendix A.1 | Q64: Foundational | S64: OpenAlex W2033910434; Crossref DOI record checked | U64: W2033910434 | V64: no
A65: S064 | B65: pynnonen2022non | C65: Pynnonen, Seppo | D65: 2022 | E65: Non-parametric statistic for testing cumulative abnormal stock returns | F65: Journal of Risk and Financial Management | G65: Journal article | H65: 10.3390/jrfm15040149 | I65: Financial market events | J65: F1 - Classical event-study econometrics | L65: 3.6 | M65: Methodological Approaches in Financial Event Research (F1) | N65: F1 | O65: Table F1 | P65: 3.6 Methodological Approaches in Financial Event Research; Appendix A.1 | Q65: Core | S65: OpenAlex W4220719043; Crossref DOI record checked | U65: W4220719043 | V65: yes | W65: development
A66: S065 | B66: nguyen2026permutation | C66: Nguyen, Phuong Anh; Wolf, Michael | D66: 2026 | E66: The permutation test for event studies with a small number of events | F66: Empirical Economics | G66: Journal article | H66: 10.1007/s00181-026-02905-6 | I66: Financial market events | J66: F1 - Classical event-study econometrics | L66: 3.6 | M66: Methodological Approaches in Financial Event Research (F1) | N66: F1 | O66: Table F1 | P66: 3.6 Methodological Approaches in Financial Event Research; Appendix A.1 | Q66: Core | S66: OpenAlex W7140172419; Crossref DOI record checked | U66: W7140172419 | V66: yes | W66: validation | X66: yes
A67: S066 | B67: kothari2007econometrics | C67: Kothari, Sagar P; Warner, Jerold B | D67: 2007 | E67: Econometrics of event studies | F67: Handbook of empirical corporate finance | G67: Book chapter | H67: 10.1016/B978-0-444-53265-7.50015-9 | I67: Financial market events | J67: F1 - Classical event-study econometrics | L67: 3.6 | M67: Methodological Approaches in Financial Event Research (F1) | N67: F1 | O67: Table F1 | P67: 3.6 Methodological Approaches in Financial Event Research; Appendix A.1 | Q67: Foundational | S67: OpenAlex W148329840; Crossref DOI record checked | U67: W148329840 | V67: no
A68: S067 | B68: goldsmith2025causal | C68: Goldsmith-Pinkham, Paul; Lyu, Tianshu | D68: 2025 | E68: Causal inference in financial event studies | F68: arXiv preprint arXiv:2511.15123 | G68: Preprint / working paper | H68: 10.48550/arXiv.2511.15123 | I68: Financial market events | J68: F1 - Classical event-study econometrics | K68: Causal Identification | L68: 3.6 | M68: Methodological Approaches in Financial Event Research (F1) | N68: F1 | O68: Table F1 | P68: 3.6 Methodological Approaches in Financial Event Research; 4.2.1 Causal Identification in Cross-Domain Research; Appendix A.1 | Q68: Core | S68: OpenAlex W7106255595; arXiv DOI (registered with DataCite, not Crossref) | U68: W7106255595 | V68: yes | W68: validation | X68: yes
A69: S068 | B69: engle1982autoregressive | C69: Engle, Robert F | D69: 1982 | E69: Autoregressive conditional heteroscedasticity with estimates of the variance of United Kingdom inflation | F69: Econometrica: Journal of the Econometric Society | G69: Journal article | H69: 10.2307/1912773 | I69: Financial market events | J69: F2 - Volatility, risk, and structural change | L69: 3.6 | M69: Methodological Approaches in Financial Event Research (F2) | N69: F2 | O69: Table F2 | P69: 3.6 Methodological Approaches in Financial Event Research; Appendix A.1 | Q69: Foundational | S69: OpenAlex W1979575715; Crossref DOI record checked | U69: W1979575715 | V69: no
A70: S069 | B70: bollerslev1986generalized | C70: Bollerslev, Tim | D70: 1986 | E70: Generalized autoregressive conditional heteroskedasticity | F70: Journal of econometrics | G70: Journal article | H70: 10.1016/0304-4076(86)90063-1 | I70: Financial market events | J70: F2 - Volatility, risk, and structural change | L70: 3.6 | M70: Methodological Approaches in Financial Event Research (F2) | N70: F2 | O70: Table F2 | P70: 3.6 Methodological Approaches in Financial Event Research; Appendix A.1 | Q70: Foundational | S70: OpenAlex W1999996900; Crossref DOI record checked | U70: W1999996900 | V70: no
A71: S070 | B71: zhu2025volatility | C71: Zhu, Min; Song, Yuping; Zheng, Xin | D71: 2025 | E71: Volatility dynamics and mixed Jump-GARCH model based jump detection in financial markets | F71: Computational Economics | G71: Journal article | H71: 10.1007/s10614-024-10633-1 | I71: Financial market events | J71: F2 - Volatility, risk, and structural change | L71: 3.6 | M71: Methodological Approaches in Financial Event Research (F2) | N71: F2 | O71: Table F2 | P71: 3.6 Methodological Approaches in Financial Event Research; Appendix A.1 | Q71: Core | S71: OpenAlex W4399703612; Crossref DOI record checked | U71: W4399703612 | V71: yes | W71: development
A72: S071 | B72: bai2003computation | C72: Bai, Jushan; Perron, Pierre | D72: 2003 | E72: Computation and analysis of multiple structural change models | F72: Journal of applied econometrics | G72: Journal article | H72: 10.1002/jae.659 | I72: Financial market events | J72: F2 - Volatility, risk, and structural change | L72: 3.6 | M72: Methodological Approaches in Financial Event Research (F2) | N72: F2 | O72: Table F2 | P72: 3.6 Methodological Approaches in Financial Event Research; 4.1.3 Event-Level Descriptors; Appendix A.1 | Q72: Foundational | S72: OpenAlex W1547068196; Crossref DOI record checked | U72: W1547068196 | V72: no
A73: S072 | B73: hasanov2024structural | C73: Hasanov, Akram Shavkatovich; Brooks, Robert; Abrorov, Sirojiddin; Burkhanov, Aktam Usmanovich | D73: 2024 | E73: Structural breaks and GARCH models of exchange rate volatility: Re-examination and extension | F73: Journal of Applied Econometrics | G73: Journal article | H73: 10.1002/jae.3091 | I73: Financial market events | J73: F2 - Volatility, risk, and structural change | L73: 3.6 | M73: Methodological Approaches in Financial Event Research (F2) | N73: F2 | O73: Table F2 | P73: 3.6 Methodological Approaches in Financial Event Research; Appendix A.1 | Q73: Core | S73: OpenAlex W4401402098; Crossref DOI record checked | U73: W4401402098 | V73: yes | W73: development
A74: S073 | B74: sun2026inference | C74: Sun, Yan; Du, Xiaobin; Zhang, Ying | D74: 2026 | E74: Inference for a multiplicative volatility model allowing for structural breaks | F74: Communications in Statistics-Simulation and Computation | G74: Journal article | H74: 10.1080/03610918.2025.2474595 | I74: Financial market events | J74: F2 - Volatility, risk, and structural change | L74: 3.6 | M74: Methodological Approaches in Financial Event Research (F2) | N74: F2 | O74: Table F2 | P74: 3.6 Methodological Approaches in Financial Event Research; 4.1.3 Event-Level Descriptors; Appendix A.1 | Q74: Core | S74: OpenAlex W4408449336; Crossref DOI record checked | U74: W4408449336 | V74: yes | W74: validation | X74: yes
A75: S074 | B75: mugrabi2026financial | C75: Mugrabi, Farah | D75: 2026 | E75: Financial contagion: Detecting non-simultaneous breaks in DCC-GARCH models | F75: International Journal of Finance & Economics | G75: Journal article | H75: 10.1002/ijfe.70064 | I75: Financial market events | J75: F2 - Volatility, risk, and structural change | L75: 3.6 | M75: Methodological Approaches in Financial Event Research (F2) | N75: F2 | O75: Table F2 | P75: 3.6 Methodological Approaches in Financial Event Research; Appendix A.1 | Q75: Core | S75: OpenAlex W4414769417; Crossref DOI record checked | U75: W4414769417 | V75: yes | W75: validation | X75: yes
A76: S075 | B76: anderson2003micro | C76: Anderson, Torben G; Bollerslev, Tim; Diebold, Francis X; Vega, Clara | D76: 2003 | E76: Micro effects of macro announcements: Real-time price discovery in foreign exchange | F76: American economic review | G76: Journal article | H76: 10.1257/000282803321455151 | I76: Financial market events | J76: F3 - High-frequency and intraday market response | L76: 3.6 | M76: Methodological Approaches in Financial Event Research (F3) | N76: F3 | O76: Table F3 | P76: 3.6 Methodological Approaches in Financial Event Research; Appendix A.1 | Q76: Foundational | S76: OpenAlex W3123647737 (matched by title); DOI corrected in .bib | T76: Corrected in surveybib_corrected.bib (2026-10-19): doi: DOI resolved to another article (Gravity with Gravitas ...) | U76: W3123647737 | V76: no
A77: S076 | B77: hasbrouck1991measuring | C77: Hasbrouck, Joel | D77: 1991 | E77: Measuring the information content of stock trades | F77: The Journal of Finance | G77: Journal article | H77: 10.1111/j.1540-6261.1991.tb03749.x | I77: Financial market events | J77: F3 - High-frequency and intraday market response | L77: 3.6 | M77: Methodological Approaches in Financial Event Research (F3) | N77: F3 | O77: Table F3 | P77: 3.6 Methodological Approaches in Financial Event Research; Appendix A.1 | Q77: Foundational | S77: OpenAlex W2108032253; Crossref DOI record checked | U77: W2108032253 | V77: no
A78: S077 | B78: bacry2015hawkes | C78: Bacry, Emmanuel; Mastromatteo, Iacopo; Muzy, Jean-François | D78: 2015 | E78: Hawkes processes in finance | F78: Market Microstructure and Liquidity | G78: Journal article | I78: Financial market events | J78: F3 - High-frequency and intraday market response | L78: 3.6 | M78: Methodological Approaches in Financial Event Research (F3) | N78: F3 | O78: Table F3 | P78: 3.6 Methodological Approaches in Financial Event Research; Appendix A.1 | Q78: Foundational | S78: OpenAlex W1594866779 (matched by title); no DOI in .bib | U78: W1594866779 | V78: no
A79: S078 | B79: nystrom2022hawkes | C79: Nyström, Kaj; Zhang, Changyong | D79: 2022 | E79: Hawkes-based models for high frequency financial data | F79: Journal of the Operational Research Society | G79: Journal article | H79: 10.1080/01605682.2021.1952116 | I79: Financial market events | J79: F3 - High-frequency and intraday market response | L79: 3.6 | M79: Methodological Approaches in Financial Event Research (F3) | N79: F3 | O79: Table F3 | P79: 3.6 Methodological Approaches in Financial Event Research; Appendix A.1 | Q79: Core | S79: OpenAlex W3186863058; Crossref DOI record checked | U79: W3186863058 | V79: yes | W79: development
A80: S079 | B80: mucciante2024estimation | C80: Mucciante, Luca; Sancetta, Alessio | D80: 2024 | E80: Estimation of an order book dependent Hawkes process for large datasets | F80: Journal of Financial Econometrics | G80: Journal article | H80: 10.1093/jjfinec/nbad021 | I80: Financial market events | J80: F3 - High-frequency and intraday market response | L80: 3.6 | M80: Methodological Approaches in Financial Event Research (F3) | N80: F3 | O80: Table F3 | P80: 3.6 Methodological Approaches in Financial Event Research; Appendix A.1 | Q80: Core | S80: OpenAlex W4385782110; Crossref DOI record checked | U80: W4385782110 | V80: yes | W80: development
A81: S080 | B81: jusselin2020no | C81: Jusselin, Paul; Rosenbaum, Mathieu | D81: 2020 | E81: No-arbitrage implies power-law market impact and rough volatility | F81: Mathematical Finance | G81: Journal article | H81: 10.1111/mafi.12254 | I81: Financial market events | J81: F3 - High-frequency and intraday market response | L81: 3.6 | M81: Methodological Approaches in Financial Event Research (F3) | N81: F3 | O81: Table F3 | P81: 3.6 Methodological Approaches in Financial Event Research; Appendix A.1 | Q81: Core | S81: OpenAlex W2803897013; Crossref DOI record checked | U81: W2803897013 | V81: no
A82: S081 | B82: gross2011machines | C82: Groß-Klußmann, Axel; Hautsch, Nikolaus | D82: 2011 | E82: When machines read the news: Using automated text analytics to quantify high frequency news-implied market reactions | F82: Journal of Empirical Finance | G82: Journal article | H82: 10.1016/j.jempfin.2010.11.009 | I82: Financial market events | J82: F3 - High-frequency and intraday market response | L82: 3.6 | M82: Methodological Approaches in Financial Event Research (F3) | N82: F3 | O82: Table F3 | P82: 3.6 Methodological Approaches in Financial Event Research; 4.2 Cross-Domain Research; Appendix A.1 | Q82: Core | S82: OpenAlex W2090588899; Crossref DOI record checked | U82: W2090588899 | V82: no
A83: S082 | B83: yang2025price | C83: Yang, Ni; Fernandez-Perez, Adrian; Indriawan, Ivan | D83: 2025 | E83: The price impact of tweets: A high-frequency study | F83: Financial Review | G83: Journal article | H83: 10.1111/fire.12406 | I83: Financial market events | J83: F3 - High-frequency and intraday market response | L83: 3.6 | M83: Methodological Approaches in Financial Event Research (F3) | N83: F3 | O83: Table F3 | P83: 3.6 Methodological Approaches in Financial Event Research; 4.2 Cross-Domain Research; Appendix A.1 | Q83: Core | S83: OpenAlex W4400112346; Crossref DOI record checked | U83: W4400112346 | V83: yes | W83: validation | X83: no
A84: S083 | B84: behrendt2018twitter | C84: Behrendt, Simon; Schmidt, Alexander | D84: 2018 | E84: The Twitter myth revisited: Intraday investor sentiment, Twitter activity and individual-level stock return volatility | F84: Journal of Banking & Finance | G84: Journal article | H84: 10.1016/j.jbankfin.2018.09.016 | I84: Financial market events | J84: F3 - High-frequency and intraday market response | L84: 3.6 | M84: Methodological Approaches in Financial Event Research (F3) | N84: F3 | O84: Table F3 | P84: 3.6 Methodological Approaches in Financial Event Research; 4.2 Cross-Domain Research; Appendix A.1 | Q84: Core | S84: OpenAlex W2892468315; Crossref DOI record checked | U84: W2892468315 | V84: no
A85: S084 | B85: tetlock2007giving | C85: Tetlock, Paul C | D85: 2007 | E85: Giving content to investor sentiment: The role of media in the stock market | F85: The Journal of finance | G85: Journal article | H85: 10.1111/j.1540-6261.2007.01232.x | I85: Financial market events | J85: F4 - Textual and attention-augmented asset pricing | L85: 3.6 | M85: Methodological Approaches in Financial Event Research (F4) | N85: F4 | O85: Table F4 | P85: 3.6 Methodological Approaches in Financial Event Research; Appendix A.1 | Q85: Foundational | S85: OpenAlex W3122944446; Crossref DOI record checked | U85: W3122944446 | V85: no
A86: S085 | B86: loughran2011liability | C86: Loughran, Tim; McDonald, Bill | D86: 2011 | E86: When is a liability not a liability? Textual analysis, dictionaries, and 10-Ks | F86: The Journal of finance | G86: Journal article | H86: 10.1111/j.1540-6261.2010.01625.x | I86: Financial market events | J86: F4 - Textual and attention-augmented asset pricing | L86: 3.6 | M86: Methodological Approaches in Financial Event Research (F4) | N86: F4 | O86: Table F4 | P86: 3.6 Methodological Approaches in Financial Event Research; Appendix A.1 | Q86: Foundational | S86: OpenAlex W2152136804; Crossref DOI record checked | U86: W2152136804 | V86: no
A87: S086 | B87: da2011search | C87: Da, Zhi; Engelberg, Joseph; Gao, Pengjie | D87: 2011 | E87: In search of attention | F87: The journal of finance | G87: Journal article | H87: 10.1111/j.1540-6261.2011.01679.x | I87: Financial market events | J87: F4 - Textual and attention-augmented asset pricing | L87: 3.6 | M87: Methodological Approaches in Financial Event Research (F4) | N87: F4 | O87: Table F4 | P87: 3.6 Methodological Approaches in Financial Event Research; Appendix A.1 | Q87: Foundational | S87: OpenAlex W3122136669; Crossref DOI record checked | U87: W3122136669 | V87: no
A88: S087 | B88: chen2014wisdom | C88: Chen, Hailiang; De, Prabuddha; Hu, Yu; Hwang, Byoung-Hyoun | D88: 2014 | E88: Wisdom of crowds: The value of stock opinions transmitted through social media | F88: The review of financial studies | G88: Journal article | H88: 10.1093/rfs/hhu001 | I88: Financial market events | J88: F4 - Textual and attention-augmented asset pricing | L88: 3.6 | M88: Methodological Approaches in Financial Event Research (F4) | N88: F4 | O88: Table F4 | P88: 3.6 Methodological Approaches in Financial Event Research; Appendix A.1 | Q88: Core | S88: OpenAlex W3124798136; Crossref DOI record checked | U88: W3124798136 | V88: no
A89: S088 | B89: liu2023social | C89: Liu, Wenwen; Yang, Jinyu; Chen, Jingrui; Xu, Lei | D89: 2023 | E89: How social-network attention and sentiment of investors affect commodity futures market returns: New evidence from China | F89: Sage Open | G89: Journal article | H89: 10.1177/21582440231152131 | I89: Financial market events | J89: F4 - Textual and attention-augmented asset pricing | L89: 3.6 | M89: Methodological Approaches in Financial Event Research (F4) | N89: F4 | O89: Table F4 | P89: 3.6 Methodological Approaches in Financial Event Research; Appendix A.1 | Q89: Core | S89: OpenAlex W4318320749; Crossref DOI record checked | U89: W4318320749 | V89: yes | W89: validation | X89: yes
A90: S089 | B90: kim2025news | C90: Kim-Hahm, Hyunsun; Abou-Zaid, Ahmed S.; Mohd, Abidalrahman | D90: 2025 | E90: News vs. Social Media: Sentiment Impact on Stock Performance of Big Tech Companies | F90: Journal of Risk and Financial Management | G90: Journal article | H90: 10.3390/jrfm18120660 | I90: Financial market events | J90: F4 - Textual and attention-augmented asset pricing | L90: 3.6 | M90: Methodological Approaches in Financial Event Research (F4) | N90: F4 | O90: Table F4 | P90: 3.6 Methodological Approaches in Financial Event Research; Appendix A.1 | Q90: Core | S90: OpenAlex W4416592915; Crossref DOI record checked | T90: Corrected in surveybib_corrected.bib (2026-10-19): title/author: Title was copied from liu2023social and authors were missing | U90: W4416592915 | V90: yes | W90: development
A91: S090 | B91: kraaijeveld2020predictive | C91: Kraaijeveld, Olivier; De Smedt, Johannes | D91: 2020 | E91: The predictive power of public Twitter sentiment for forecasting cryptocurrency prices | F91: Journal of International Financial Markets, Institutions and Money | G91: Journal article | H91: 10.1016/j.intfin.2020.101188 | I91: Financial market events | J91: F4 - Textual and attention-augmented asset pricing | L91: 3.6 | M91: Methodological Approaches in Financial Event Research (F4) | N91: F4 | O91: Table F4 | P91: 3.6 Methodological Approaches in Financial Event Research; Appendix A.1 | Q91: Core | S91: OpenAlex W3011605097; Crossref DOI record checked | U91: W3011605097 | V91: no
A92: S091 | B92: arnold2022attention | C92: Arnold, Marc; Pelster, Matthias; Subrahmanyam, Marti G | D92: 2022 | E92: Attention triggers and investors’ risk-taking | F92: Journal of Financial Economics | G92: Journal article | H92: 10.1016/j.jfineco.2021.05.031 | I92: Financial market events | J92: F4 - Textual and attention-augmented asset pricing | L92: 3.6 | M92: Methodological Approaches in Financial Event Research (F4) | N92: F4 | O92: Table F4 | P92: 3.6 Methodological Approaches in Financial Event Research; Appendix A.1 | Q92: Core | S92: OpenAlex W3118192601; Crossref DOI record checked | U92: W3118192601 | V92: yes | W92: development
A93: S092 | B93: xu2019anatomy | C93: Xu, Jiahua; Livshits, Benjamin | D93: 2019 | E93: The anatomy of a cryptocurrency Pump-and-Dump scheme | F93: 28th USENIX Security Symposium (USENIX Security 19) | G93: Conference paper | I93: Financial market events | J93: F5 - Market manipulation and abusive trading detection | K93: Cross-Domain Challenges | L93: 3.6 | M93: Methodological Approaches in Financial Event Research (F5) | N93: F5 | O93: Table F5 | P93: 3.6 Methodological Approaches in Financial Event Research; 4.1.3 Event-Level Descriptors; 4.2 Cross-Domain Research; Appendix A.1 | Q93: Core | S93: OpenAlex W2900601813 (matched by title); no DOI in .bib | U93: W2900601813 | V93: no
A94: S093 | B94: kogan2023social | C94: Kogan, Shimon; Moskowitz, Tobias J; Niessner, Marina | D94: 2023 | E94: Social media and financial news manipulation | F94: Review of Finance | G94: Journal article | H94: 10.1093/rof/rfac058 | I94: Financial market events | J94: F5 - Market manipulation and abusive trading detection | L94: 3.6 | M94: Methodological Approaches in Financial Event Research (F5) | N94: F5 | O94: Table F5 | P94: 1.1 Background and Motivation; 3.6 Methodological Approaches in Financial Event Research; Appendix A.1 | Q94: Core | S94: OpenAlex W3200102637 (matched by title); DOI corrected in .bib | T94: Corrected in surveybib_corrected.bib (2026-10-19): doi: DOI resolved to another article (Income, Liquidity, and the Consumption Response ...) | U94: W3200102637 | V94: yes | W94: development
A95: S094 | B95: leuz2026falls | C95: Leuz, Christian; Meyer, Steffen; Muhn, Maximilian; Soltes, Eugene; Hackethal, Andreas | D95: 2026 | E95: Who falls prey to the Wolf of Wall Street? Investor participation in market manipulation | F95: Management Science | G95: Journal article | H95: 10.1287/mnsc.2023.03181 | I95: Financial market events | J95: F5 - Market manipulation and abusive trading detection | L95: 3.6 | M95: Methodological Approaches in Financial Event Research (F5) | N95: F5 | O95: Table F5 | P95: 3.6 Methodological Approaches in Financial Event Research; Appendix A.1 | Q95: Core | S95: OpenAlex W4416210187; Crossref DOI record checked | U95: W4416210187 | V95: yes | W95: development
A96: S095 | B96: li2025cryptocurrency | C96: Li, Tao; Shin, Donghwa; Wang, Baolian | D96: 2025 | E96: Cryptocurrency pump-and-dump schemes | F96: Journal of Financial and Quantitative Analysis | G96: Journal article | H96: 10.1017/S0022109025000201 | I96: Financial market events | J96: F5 - Market manipulation and abusive trading detection | K96: Causal Identification | L96: 3.6 | M96: Methodological Approaches in Financial Event Research (F5) | N96: F5 | O96: Table F5 | P96: 3.6 Methodological Approaches in Financial Event Research; 4.1.3 Event-Level Descriptors; 4.2 Cross-Domain Research; 4.2.1 Causal Identification in Cross-Domain Research; Appendix A.1 | Q96: Core | S96: OpenAlex W4409174306; Crossref DOI record checked | U96: W4409174306 | V96: yes | W96: development
A97: S096 | B97: la2023doge | C97: La Morgia, Massimo; Mei, Alessandro; Sassi, Francesco; Stefa, Julinda | D97: 2023 | E97: The Doge of Wall Street: Analysis and detection of pump-and-dump cryptocurrency manipulations | F97: ACM Transactions on Internet Technology | G97: Journal article | H97: 10.1145/3561300 | I97: Financial market events | J97: F5 - Market manipulation and abusive trading detection | L97: 3.6 | M97: Methodological Approaches in Financial Event Research (F5) | N97: F5 | O97: Table F5 | P97: 3.6 Methodological Approaches in Financial Event Research; 4.2 Cross-Domain Research; Appendix A.1 | Q97: Core | S97: OpenAlex W3159176111; Crossref DOI record checked | U97: W3159176111 | V97: yes | W97: validation | X97: yes
A98: S097 | B98: bradley2024place | C98: Bradley, Daniel; Hanousek Jr, Jan; Jame, Russell; Xiao, Zicheng | D98: 2024 | E98: Place your bets? The value of investment research on Reddit's WallStreetBets | F98: The Review of Financial Studies | G98: Journal article | H98: 10.1093/rfs/hhad098 | I98: Financial market events | J98: F5 - Market manipulation and abusive trading detection | L98: 3.6 | M98: Methodological Approaches in Financial Event Research (F5) | N98: F5 | O98: Table F5 | P98: 3.6 Methodological Approaches in Financial Event Research; Appendix A.1 | Q98: Core | S98: OpenAlex W4390043602; Crossref DOI record checked | U98: W4390043602 | V98: yes | W98: validation | X98: no
A99: S098 | B99: keasey2025impact | C99: Keasey, Kevin; Lambrinoudakis, Costas; Mascia, Danilo V; Zhang, Zhengfa | D99: 2025 | E99: The impact of social media influencers on the financial market performance of firms | F99: European Financial Management | G99: Journal article | H99: 10.1111/eufm.12513 | I99: Financial market events | J99: F5 - Market manipulation and abusive trading detection | L99: 3.6 | M99: Methodological Approaches in Financial Event Research (F5) | N99: F5 | O99: Table F5 | P99: 3.6 Methodological Approaches in Financial Event Research; 4.2 Cross-Domain Research; Appendix A.1 | Q99: Core | S99: OpenAlex W4402517944; Crossref DOI record checked | U99: W4402517944 | V99: yes | W99: development
A100: S099 | B100: roy2024unveiling | C100: Roy, Sayak Saha; Das, Dipanjan; Bose, Priyanka; Kruegel, Christopher; Vigna, Giovanni; Nilizadeh, Shirin | D100: 2024 | E100: Unveiling the risks of NFT promotion scams | F100: Proceedings of the International AAAI Conference on Web and Social Media | G100: Conference paper | H100: 10.1609/icwsm.v18i1.31395 | I100: Financial market events | J100: F5 - Market manipulation and abusive trading detection | L100: 3.6 | M100: Methodological Approaches in Financial Event Research (F5) | N100: F5 | O100: Table F5 | P100: 3.6 Methodological Approaches in Financial Event Research; Appendix A.1 | Q100: Core | S100: OpenAlex W4399205260; Crossref DOI record checked | U100: W4399205260 | V100: yes | W100: validation | X100: no
...

Sheet not_in_corpus
A1: bibkey | B1: authors | C1: year | D1: title | E1: publication_type | F1: doi | G1: cited_in_section | H1: reason not in corpus
A2: kumar2018false | B2: Kumar, Srijan; Shah, Neil | C2: 2018 | D2: False information on web and social media: A survey | E2: Preprint / working paper | F2: 10.48550/arXiv.1804.08559 | G2: 1.1 | H2: Background and motivation (information ecosystem). Cited outside the sections counted in the PRISMA categories.
A3: armstrong2019organized | B3: Armstrong, Jeremy | C3: 2019 | D3: Organized chaos: manipuli, socii, and the Roman army c. 300 | E3: Book chapter | F3: 10.4324/9781351063500-5 | G3: 1.1 | H3: Historical motivation; possible citation-claim mismatch (chapter title concerns Roman army organisation). Cited outside the sections counted in the PRISMA categories.
A4: nam2025detecting | B4: Nam, D; Skillicorn, David B | C4: 2025 | D4: Detecting Pump &Dump stock market manipulation from online forums | E4: Journal article | F4: 10.1007/s42521-024-00121-4 | G4: 1.2 | H4: Background (algorithmic amplification). Cited outside the sections counted in the PRISMA categories.
A5: silva2025guidelines | B5: Silva, Marcus VS; dos Santos, Luiz FC; Soares, Michel S; Rocha, Fabio Gomes | C5: 2025 | D5: Guidelines for the Application of Event Driven Architecture in Micro Services with High Volume of Data | E5: Conference paper | F5: 10.5220/0013348600003929 | G5: 1.2 | H5: Software-engineering motivation. Cited outside the sections counted in the PRISMA categories.
A6: nazir2024architecting | B6: Nazir, Roger; Bucaioni, Alessio; Pelliccione, Patrizio | C6: 2024 | D6: Architecting ML-enabled systems: Challenges, best practices, and design decisions | E6: Journal article | F6: 10.1016/j.jss.2023.111860 | G6: 1.2 | H6: Software-engineering motivation. Cited outside the sections counted in the PRISMA categories.
A7: rahman2025secureai | B7: Abdur Rahman; Md. Badiuzzaman Biplob | C7: 2025 | D7: SecureAI-Flow: A Security-Oriented CI/CD Framework for AI Software | E7: Preprint / working paper | F7: 10.20944/preprints202506.0035.v1 | G7: 1.2 | H7: Software-engineering motivation. Cited outside the sections counted in the PRISMA categories.
A8: chen2025year | B8: Chen, Yisong; Zhao, Chuqing; Xu, Yixin; Nie, Chuanhao | C8: 2025 | D8: Year-over-year developments in financial fraud detection via deep learning: A systematic literature review | E8: Preprint / working paper | F8: 10.48550/arXiv.2502.00201 | G8: 1.2 | H8: Motivation (experimental prototypes). Cited outside the sections counted in the PRISMA categories.
A9: Cortis2020SocialOpinionMining | B9: Cortis, Keith; Davis, Brian | C9: 2020 | D9: Over a decade of social opinion mining: a systematic review | E9: Journal article | F9: 10.1007/s10462-020-09864-2 | G9: 1.4 | H9: Prior survey used to position the review. Cited outside the sections counted in the PRISMA categories.
A10: Reveilhac2022SocialMediaSurveys | B10: Reveilhac, Maud; Steinmetz, Stephanie; Morselli, Davide | C10: 2022 | D10: A systematic literature review of how and whether social media data can complement traditional survey data to study public opinion | E10: Journal article | F10: 10.1007/s11042-022-12121-3 | G10: 1.4 | H10: Prior survey used to position the review. Cited outside the sections counted in the PRISMA categories.
A11: Abkenar2020BigDataSocialMedia | B11: Bazzaz Abkenar, Sepideh; Kashani, Mohammad Hossein; Mahdipour, Ebrahim; Jameii, Seyed Mohammad | C11: 2020 | D11: Big data analytics meets social media: A systematic review of techniques, open issues, and future directions | E11: Journal article | F11: 10.1016/j.tele.2020.101517 | G11: 1.4 | H11: Prior survey used to position the review. Cited outside the sections counted in the PRISMA categories.
A12: Rahman2022SystematicReviewBigDataSocialMedia | B12: Rahman, Md. Saifur; Reza, Hassan | C12: 2022 | D12: A Systematic Review Towards Big Data Analytics in Social Media | E12: Journal article | F12: 10.26599/BDMA.2022.9020019 | G12: 1.4 | H12: Prior survey used to position the review. Cited outside the sections counted in the PRISMA categories.
A13: Long2025SocialMediaCapitalMarkets | B13: Long, Wen; Guo, Man | C13: 2025 | D13: Social media and capital markets: an interdisciplinary bibliometric analysis | E13: Journal article | F13: 10.1186/s40854-024-00731-2 | G13: 1.4 | H13: Prior survey used to position the review. Cited outside the sections counted in the PRISMA categories.
... A18: hinderks2020slr | B18: Hinderks, Andreas; Mayo, Francisco José Domínguez; Thomaschewski, Jörg; Escalona, María José | C18: 2020 | D18: An SLR-Tool: Search process in practice: A tool to conduct and manage systematic literature review (SLR) | E18: Conference paper | F18: 10.1145/3377812.3382137 | G18: 2 | H18: SLR methodology guideline. Cited outside the sections counted in the PRISMA categories.
A19: stapic2012performing | B19: Stapic, Zlatko; López, Eva García; Cabot, Antonio García; de Marcos Ortega, Luis; Strahonja, Vjeran | C19: 2012 | D19: Performing systematic literature review in software engineering | E19: Conference paper | G19: 2 | H19: SLR methodology guideline. Cited outside the sections counted in the PRISMA categories.
A20: page2021prisma | B20: Page, Matthew J; McKenzie, Joanne E; Bossuyt, Patrick M; Boutron, Isabelle; Hoffmann, Tammy C; Mulrow, Cynthia D; Shamseer, Larissa; Tetzlaff, Jennifer M; Akl, Elie A; Brennan, Sue E; et al. | C20: 2021 | D20: The PRISMA 2020 statement: An updated guideline for reporting systematic reviews | E20: Journal article | F20: 10.1136/bmj.n71 | G20: 2.2 | H20: PRISMA 2020 reporting guideline. Cited outside the sections counted in the PRISMA categories.
A21: hausner2012routine | B21: Hausner, Elke; Waffenschmidt, Siw; Kaiser, Thomas; Simon, Michael | C21: 2012 | D21: Routine development of objectively derived search strategies | E21: Journal article | F21: 10.1186/2046-4053-1-19 | G21: 2 (Reproducibility of the Review) | H21: Method for objectively derived search strategies (known-item retrieval check); cited in the revision. Cited outside the sections counted in the PRISMA categories.

Sheet codebook
A1: column | B1: label | C1: definition
A2: study_id | C2: Sequential identifier in manuscript order (S001-S126).
A3: bibkey | C3: Citation key exactly as used in the manuscript and surveybib.bib.
A4: publication_type | B4: Journal article / Conference paper / Book / Book chapter / Preprint / working paper | C4: Taken from the BibTeX entry type and venue field, as used for the corpus-composition table.
A5: theme | B5: Social media analysis / Financial market events / Cross-Domain Events and Causality | C5: The three groups of the PRISMA flow diagram ("Included studies categorized by conceptual theme").
A6: prisma_box | B6: 17 categories | C6: The category box of the PRISMA diagram in which the study is counted. Each study is counted once, in the first section where it is analysed.
A7: xref_to | C7: Further PRISMA category in which the study is also analysed. These are the "overlapping studies" shown in the diagram (2 in Financial signals, 1 in Cross-Domain Challenges, 5 in Causal Identification).
A8: section_no / section | C8: Manuscript section that corresponds to the PRISMA category.
A9: method_class | B9: C1-C6, F1-F5 | C9: Methodological class; assigned only where the study is listed in an appendix table.
A10: cited_in | C10: All manuscript sections in which the study is cited.
A11: study_role | B11: Core | C11: Findings or contributions analysed to characterise the state of research.
A12: study_role | B12: Foundational | C12: Cited as the origin or standard reference of a definition, model or statistical method; included by the rule in Section 2.2 on foundational works.
A13: revision_status | B13: restored to text in revision | C13: Study belonged to the corpus counted in the PRISMA diagram; its citation had been lost from the text during revision and was restored.
A14: metadata_check | C14: Result of the metadata check of 19 October 2026: OpenAlex work ID, and whether the DOI record was checked in Crossref. Bibliographic data are taken from surveybib_corrected.bib.
A15: note | C15: Correction applied to the .bib entry, or a remaining point to verify.
A16: openalex_id | C16: OpenAlex work identifier (https://openalex.org/<id>). Empty = not indexed in OpenAlex.
A17: in_search_window | B17: yes / no | C17: Publication year 2021-2026 (the database search window, Section 2.2). Only these studies enter the known-item retrieval check; older works are foundational works included through citation searching.
A18: validation_set | B18: development / validation | C18: Set of the known-item retrieval check (studies published 2021-2026 only; split at random within each PRISMA category, seed 20261019). Development titles were used to derive the query; validation studies were used only to evaluate it.
A19: retrieved_by_final_query | B19: yes / no / not indexed in OpenAlex | C19: Validation set only: whether the final query of the known-item retrieval check (sheet validation_result: term query with the date, document-type and subject-field restrictions) returned the study in OpenAlex on 20 October 2026. Empty for the development set, whose titles were used to build the query (development set: 42 of 44 retrieved).

Sheet class_definitions
A1: class | B1: name (manuscript heading) | C1: definition (quoted from the manuscript) | D1: manuscript section | E1: appendix table | F1: studies in register
A2: C1 | B2: Mathematical and System-Dynamics Modeling of Opinion Manipulation | C2: The first class approaches opinion manipulation as a dynamic process that can be described using formal mathematical models. In this line of work, the main objective is not to classify individual posts or claims, but to understand how opinions change over time, when instability emerges, and under which conditions misinformation becomes dominant or polarization intensifies. | D2: 3.4 Opinion Detection and Modeling | E2: Table C1 | F2: =COUNTIF(Data!$N$2:$N$127,A2) -> 6
A3: C2 | B3: Statistical Machine Learning and Deep Learning Content Detection | C3: The second class treats opinion manipulation primarily as a content detection problem. Here the central task is to determine whether a post, article, claim, or rumor is false, misleading, or otherwise suspicious by learning patterns from text and related contextual information. | D3: 3.4 Opinion Detection and Modeling | E3: Table C2 | F3: =COUNTIF(Data!$N$2:$N$127,A3) -> 8
A4: C3 | B4: Hybrid Human-AI Annotation and Verification | C4: The third class arises because manipulation is not always detectable by automatic classification. Context-sensitive claims and rhetorical devices frequently require human interpretation. | D4: 3.4 Opinion Detection and Modeling | E4: Table C3 | F4: =COUNTIF(Data!$N$2:$N$127,A4) -> 6
A5: C4 | B5: Network Structure and Propagation Analysis | C5: The fourth class of studies examines opinion manipulation via patterns of diffusion, community structures, and actor roles. In these studies, misinformation is no longer considered a characteristic of a given piece of text, but rather a phenomenon in terms of how it diffuses within a social group, who promotes it, and how network structures influence its persistence and spread. | D5: 3.4 Opinion Detection and Modeling | E5: Table C4 | F5: =COUNTIF(Data!$N$2:$N$127,A5) -> 8
A6: C5 | B6: Behavioral and Psychological Modeling | C6: The fifth class examines manipulation from the perspective of the user, rather than focusing on the message or the network. The main question is why some people are more vulnerable to misleading information, more likely to believe it, and more affected emotionally and behaviorally. | D6: 3.4 Opinion Detection and Modeling | E6: Table C5 | F6: =COUNTIF(Data!$N$2:$N$127,A6) -> 8
A7: C6 | B7: Intervention and Inoculation Strategies | C7: The sixth class brings the discussion from explanation to response. Instead of asking how manipulation works or why people are vulnerable, these studies test strategies intended to weaken manipulation, improve resistance, or redesign the environment in which misinformation spreads. | D7: 3.4 Opinion Detection and Modeling | E7: Table C6 | F7: =COUNTIF(Data!$N$2:$N$127,A7) -> 8
A8: F1 | B8: Classical event-study econometrics | C8: Classical event studies evaluate whether an externally identified event is associated with abnormal security returns. | D8: 3.6 Methodological Approaches in Financial Event Research | E8: Table F1 | F8: =COUNTIF(Data!$N$2:$N$127,A8) -> 8
A9: F2 | B9: Volatility, risk, and structural change | C9: Financial events may also appear as changes in volatility or in the parameters governing the return-generating process rather than as directional changes in mean returns. | D9: 3.6 Methodological Approaches in Financial Event Research | E9: Table F2 | F9: =COUNTIF(Data!$N$2:$N$127,A9) -> 7
A10: F3 | B10: High-frequency and intraday market response | C10: High-frequency approaches reduce the observation window from days to minutes, seconds, or transaction time, thereby allowing more precise analysis of how markets react around information arrivals. | D10: 3.6 Methodological Approaches in Financial Event Research | E10: Table F3 | F10: =COUNTIF(Data!$N$2:$N$127,A10) -> 9
A11: F4 | B11: Textual and attention-augmented asset pricing | C11: A fourth group converts information itself into measurable financial signals. | D11: 3.6 Methodological Approaches in Financial Event Research | E11: Table F4 | F11: =COUNTIF(Data!$N$2:$N$127,A11) -> 8
A12: F5 | B12: Market manipulation and abusive trading detection | C12: The final group concerns information or trading activity intentionally designed to influence market behavior. | D12: 3.6 Methodological Approaches in Financial Event Research | E12: Table F5 | F12: =COUNTIF(Data!$N$2:$N$127,A12) -> 8
E13: Total | F13: =SUM(F2:F12) -> 84
A15: Assignment: each of the 84 studies listed in the appendix tables is assigned to exactly one class (it appears in one appendix table). Studies were coded and classified by the first author according to their thematic focus and methodological characteristics, and the classifications were reviewed by the research supervisors; ambiguous cases were discussed jointly until agreement was reached (Section 2.2). The manuscript does not report an agreement statistic.
A16: The other 42 included studies (opinion and its manipulation, social-media and financial signals, cross-domain challenges, causal identification) are not assigned to a class (column method_class empty on Data).

Sheet Counts
A1: Publication type | B1: Reported (corpus-composition table) | C1: Register | D1: Difference
A2: Journal article | B2: 103 | C2: =COUNTIF(Data!$G$2:$G$127,A2) -> 103 | D2: =C2-B2 -> 0
A3: Conference paper | B3: 7 | C3: =COUNTIF(Data!$G$2:$G$127,A3) -> 7 | D3: =C3-B3 -> 0
A4: Book | B4: 3 | C4: =COUNTIF(Data!$G$2:$G$127,A4) -> 3 | D4: =C4-B4 -> 0
A5: Book chapter | B5: 2 | C5: =COUNTIF(Data!$G$2:$G$127,A5) -> 2 | D5: =C5-B5 -> 0
A6: Preprint / working paper | B6: 11 | C6: =COUNTIF(Data!$G$2:$G$127,A6) -> 11 | D6: =C6-B6 -> 0
A7: Total | B7: =SUM(B2:B6) -> 126 | C7: =SUM(C2:C6) -> 126 | D7: =SUM(D2:D6) -> 0
A9: Theme | B9: Reported (PRISMA diagram) | C9: Register | D9: Difference
A10: Social media analysis | B10: 59 | C10: =COUNTIF(Data!$I$2:$I$127,A10) -> 59 | D10: =C10-B10 -> 0
A11: Financial market events | B11: 40 | C11: =COUNTIF(Data!$I$2:$I$127,A11) -> 40 | D11: =C11-B11 -> 0
A12: Cross-Domain Events and Causality | B12: 27 | C12: =COUNTIF(Data!$I$2:$I$127,A12) -> 27 | D12: =C12-B12 -> 0
A13: Total | B13: =SUM(B10:B12) -> 126 | C13: =SUM(C10:C12) -> 126 | D13: =SUM(D10:D12) -> 0
A15: Study role | C15: Register
A16: Core | C16: =COUNTIF(Data!$Q$2:$Q$127,A16) -> 89
A17: Foundational | C17: =COUNTIF(Data!$Q$2:$Q$127,A17) -> 37
A19: Publication years (min / max) | B19: Reported: 1969-2026 | C19: =MIN(Data!$D$2:$D$127)&"-"&MAX(Data!$D$2:$D$127) -> 1969-2026
A21: OpenAlex (metadata check and retrieval check) | C21: Register
A22: Included studies published 2021-2026 (search window) | C22: =COUNTIF(Data!$V$2:$V$127,"yes") -> 82
A23: of which indexed in OpenAlex | C23: =COUNTIFS(Data!$V$2:$V$127,"yes",Data!$U$2:$U$127,"<>") -> 80
A24: Studies (of 126) indexed in OpenAlex (metadata check) | C24: =COUNTIF(Data!$U$2:$U$127,"<>") -> 122
A30: Blue = value reported in the manuscript; black = computed from the Data sheet.

Sheet PRISMA_check
A1: Theme | B1: PRISMA category | C1: Diagram: n | D1: Diagram: overlapping | E1: Register: counted here | F1: Register: overlapping | G1: Register: n | H1: Match
A2: Social media analysis | B2: Opinion in Social Networks | C2: 9 | D2: 0 | E2: =COUNTIF(Data!$J$2:$J$127,B2) -> 9 | F2: =SUMPRODUCT(--ISNUMBER(SEARCH(B2,Data!$K$2:$K$127))) -> 0 | G2: =E2+F2 -> 9 | H2: =IF(AND(G2=C2,F2=D2),"yes","NO") -> yes
A3: Social media analysis | B3: Opinion Manipulation: Definition and Typologies | C3: 6 | D3: 0 | E3: =COUNTIF(Data!$J$2:$J$127,B3) -> 6 | F3: =SUMPRODUCT(--ISNUMBER(SEARCH(B3,Data!$K$2:$K$127))) -> 0 | G3: =E3+F3 -> 6 | H3: =IF(AND(G3=C3,F3=D3),"yes","NO") -> yes
A4: Social media analysis | B4: Class 1 - Mathematical and System-Dynamics Modelling | C4: 6 | D4: 0 | E4: =COUNTIF(Data!$J$2:$J$127,B4) -> 6 | F4: =SUMPRODUCT(--ISNUMBER(SEARCH(B4,Data!$K$2:$K$127))) -> 0 | G4: =E4+F4 -> 6 | H4: =IF(AND(G4=C4,F4=D4),"yes","NO") -> yes
A5: Social media analysis | B5: Class 2 - Machine & Deep Learning Content Detection | C5: 8 | D5: 0 | E5: =COUNTIF(Data!$J$2:$J$127,B5) -> 8 | F5: =SUMPRODUCT(--ISNUMBER(SEARCH(B5,Data!$K$2:$K$127))) -> 0 | G5: =E5+F5 -> 8 | H5: =IF(AND(G5=C5,F5=D5),"yes","NO") -> yes
A6: Social media analysis | B6: Class 3 - Hybrid Human-AI Annotation and Verification | C6: 6 | D6: 0 | E6: =COUNTIF(Data!$J$2:$J$127,B6) -> 6 | F6: =SUMPRODUCT(--ISNUMBER(SEARCH(B6,Data!$K$2:$K$127))) -> 0 | G6: =E6+F6 -> 6 | H6: =IF(AND(G6=C6,F6=D6),"yes","NO") -> yes
A7: Social media analysis | B7: Class 4 - Network Structure and Propagation Analysis | C7: 8 | D7: 0 | E7: =COUNTIF(Data!$J$2:$J$127,B7) -> 8 | F7: =SUMPRODUCT(--ISNUMBER(SEARCH(B7,Data!$K$2:$K$127))) -> 0 | G7: =E7+F7 -> 8 | H7: =IF(AND(G7=C7,F7=D7),"yes","NO") -> yes
A8: Social media analysis | B8: Class 5 - Behavioural and Psychological Modelling | C8: 8 | D8: 0 | E8: =COUNTIF(Data!$J$2:$J$127,B8) -> 8 | F8: =SUMPRODUCT(--ISNUMBER(SEARCH(B8,Data!$K$2:$K$127))) -> 0 | G8: =E8+F8 -> 8 | H8: =IF(AND(G8=C8,F8=D8),"yes","NO") -> yes
A9: Social media analysis | B9: Class 6 - Intervention and Inoculation Strategies | C9: 8 | D9: 0 | E9: =COUNTIF(Data!$J$2:$J$127,B9) -> 8 | F9: =SUMPRODUCT(--ISNUMBER(SEARCH(B9,Data!$K$2:$K$127))) -> 0 | G9: =E9+F9 -> 8 | H9: =IF(AND(G9=C9,F9=D9),"yes","NO") -> yes
A10: Financial market events | B10: F1 - Classical event-study econometrics | C10: 8 | D10: 0 | E10: =COUNTIF(Data!$J$2:$J$127,B10) -> 8 | F10: =SUMPRODUCT(--ISNUMBER(SEARCH(B10,Data!$K$2:$K$127))) -> 0 | G10: =E10+F10 -> 8 | H10: =IF(AND(G10=C10,F10=D10),"yes","NO") -> yes
A11: Financial market events | B11: F2 - Volatility, risk, and structural change | C11: 7 | D11: 0 | E11: =COUNTIF(Data!$J$2:$J$127,B11) -> 7 | F11: =SUMPRODUCT(--ISNUMBER(SEARCH(B11,Data!$K$2:$K$127))) -> 0 | G11: =E11+F11 -> 7 | H11: =IF(AND(G11=C11,F11=D11),"yes","NO") -> yes
A12: Financial market events | B12: F3 - High-frequency and intraday market response | C12: 9 | D12: 0 | E12: =COUNTIF(Data!$J$2:$J$127,B12) -> 9 | F12: =SUMPRODUCT(--ISNUMBER(SEARCH(B12,Data!$K$2:$K$127))) -> 0 | G12: =E12+F12 -> 9 | H12: =IF(AND(G12=C12,F12=D12),"yes","NO") -> yes
A13: Financial market events | B13: F4 - Textual and attention-augmented asset pricing | C13: 8 | D13: 0 | E13: =COUNTIF(Data!$J$2:$J$127,B13) -> 8 | F13: =SUMPRODUCT(--ISNUMBER(SEARCH(B13,Data!$K$2:$K$127))) -> 0 | G13: =E13+F13 -> 8 | H13: =IF(AND(G13=C13,F13=D13),"yes","NO") -> yes
... A18: Cross-Domain Events and Causality | B18: Causal Identification | C18: 19 | D18: 5 | E18: =COUNTIF(Data!$J$2:$J$127,B18) -> 14 | F18: =SUMPRODUCT(--ISNUMBER(SEARCH(B18,Data!$K$2:$K$127))) -> 5 | G18: =E18+F18 -> 19 | H18: =IF(AND(G18=C18,F18=D18),"yes","NO") -> yes
B19: Total studies (each counted once) | C19: 126 | E19: =SUM(E2:E18) -> 126 | H19: =IF(E19=C19,"yes","NO") -> yes

Sheet search_concepts_table2
A1: concept | B1: keywords and synonyms | C1: representative Boolean string (as reported) | D1: records (as reported)
A2: Social Media Manipulation | B2: misinformation, disinformation, fake news, propaganda, opinion manipulation, influence operations | C2: ("social media" OR "online social networks") AND (misinformation OR disinformation OR "fake news" OR propaganda OR "opinion manipulation") | D2: 1667
A3: Opinion Dynamics in Networks | B3: opinion dynamics, social influence, information diffusion, consensus formation, bounded confidence | C3: ("opinion dynamics" OR "information diffusion" OR "social influence") AND ("social networks" OR "online social networks") | D3: 762
A4: Event Detection in Social Media | B4: event detection, burst detection, topic detection, social media events, event extraction | C4: ("event detection" OR "bursty events" OR "event extraction") AND ("social media" OR "online social networks") | D4: 172
A5: Fake News and Propaganda Detection | B5: fake news detection, propaganda detection, rumor detection, misinformation classification | C5: ("fake news detection" OR "propaganda detection" OR "rumor detection") AND ("social media" OR "online platforms") | D5: 382
A6: Financial Events and Market Responses | B6: event studies, abnormal returns, volatility, structural changes, high-frequency market responses | C6: ("event study" OR "financial event" OR "market event" OR "information event") AND ("abnormal return" OR volatility OR "structural break" OR "market reaction") | D6: 1066
A7: Social Media and Financial Markets | B7: investor sentiment, investor attention, misinformation, market manipulation, pump and dump, market reactions | C7: ("social media" OR Twitter OR Reddit OR Telegram) AND ("stock market" OR "financial market" OR cryptocurrency) AND ("market reaction" OR "market impact" OR "price impact" OR "return predictability" OR "market manipulation") | D7: 530
C8: Total | D8: =SUM(D2:D7) -> 4579
A10: Source: search-concepts table (tab:search_concepts), Section 2.2. They are not the query of the known-item retrieval check.

Sheet search_protocol
A1: # Known-item retrieval check: protocol
A3: Retrospective check of whether the included studies of the review can be retrieved in OpenAlex by a
A4: title query that is derived by fixed rules from part of the included studies and tested on the others
A5: (objective approach of Hausner E, Waffenschmidt S, Kaiser T, Simon M. Routine development of
A6: objectively derived search strategies. Systematic Reviews 2012;1:19. doi:10.1186/2046-4053-1-19).
A8: This experiment measures known-item retrieval within the previously selected corpus. Because both the
A9: development and validation samples originate from that corpus, the results are conditional on the
A10: original study-selection process and cannot establish the completeness, representativeness, or
A11: sensitivity of the original systematic search. The check does not reproduce the original search of
A12: the review (Section 2.2, Table 2 and the PRISMA diagram of the manuscript). Section 8 records when each
A13: rule was fixed.
A15: ## 1. Population and split (split_corpus.py)
... A145: selection bias.

Sheet validation_result
A1: item | B1: value
A2: protocol | B2: search_protocol (PROTOCOL.md). Term query, threshold, date and document-type restrictions fixed on 19 October 2026 before any count; subject-field restriction added on 20 October 2026 after earlier runs; a language filter was tested and dropped (sheet protocol_history).
A3: what the check measures | B3: Known-item retrieval within the previously selected corpus. Because both the development and validation samples originate from that corpus, the results are conditional on the original study selection and cannot establish the completeness, representativeness or sensitivity of the original systematic search.
A4: database | B4: OpenAlex, title search (title.search). Term query frozen on 19 October 2026; final run on 20 October 2026 (run_final.py).
A5: date restriction | B5: from_publication_date:2020-01-01,to_publication_date:2026-12-31 - one year before the 2021-2026 window of the included studies, because OpenAlex dates some works by their first online or preprint version (among the 82 studies, arnold2022attention, published in 2022, is dated 2020 in OpenAlex; no validation study is dated before 2021).
A6: document-type restriction | B6: type:!dissertation,type:!dataset,type:!paratext,type:!editorial,type:!letter,type:!erratum,type:!peer-review,type:!retraction - all other types (journal articles, conference papers, books, book chapters, preprints) are kept.
A7: subject-field restriction | B7: Not an eligibility criterion; used to reduce the number of records. OpenAlex field of the primary topic, kept if it is the field of at least one development study: Social Sciences (23 development studies); Economics, Econometrics and Finance (15 development studies); Computer Science (3 development studies); Physics and Astronomy (2 development studies); Decision Sciences (1 development studies). Chosen after the fields of the validation studies had been inspected, so not independently validated.
A8: language restriction | B8: none. OpenAlex leaves some works without a language, and a language filter would exclude two included studies (cui2025toward, goldsmith2025causal); the English-language criterion is applied at screening.
A9: N (works with the date and type restrictions; used for the ratios) | B9: 71,319,636
A10: threshold R (chosen on the development set) | B10: 100
A11: frozen term query (27 terms) | B11: causal OR chamber OR chatbot OR cryptocurrency OR disinformation OR echo OR "event studies" OR fake OR "financial market" OR garch OR hawkes OR "influence operations" OR investor OR manipulation OR misinformation OR news OR "online social networks" OR opinion OR propaganda OR "pump and dump" OR reddit OR rumor OR sentiment OR "social networks" OR stock OR "structural break" OR twitter
A12: term query SHA-256 | B12: 51377ba9737a1b12a8a0b8878bb0c5a27f32e47ad78dd6255a59cf54fb06a7f6 (documents the exact query run; it does not by itself show that the configuration was chosen independently of the validation results)
A13: records returned | B13: 311,556 (without the subject-field restriction on the same day: 528,902; removed by the restriction: 217,346, 41.1%)
A14: records not tagged as English (descriptive) | B14: 63,578 (20.4%; another language or no language assigned)
A15: validation set, all (primary outcome) | B15: 29/38 = 76.3% (95% CI 60.8%-87.0%)
A16: validation set, indexed in OpenAlex | B16: 29/36 = 80.6% (95% CI 65.0%-90.2%)
A17: development set | B17: 42/44 = 95.5% (95% CI 84.9%-98.7%)
A18: validation studies indexed in OpenAlex but not retrieved (7) | B18: hrckova2025autonomation; liu2024exploring; smith2024unraveling; su2025emotionally; yang2025price; bradley2024place; roy2024unveiling
A19: validation studies not indexed in OpenAlex (2) | B19: cayuela2025influence; kumarsocial
A20: interpretation | B20: The subject-field restriction did not remove any of the known included studies retrieved by the original query: the original pre-specified configuration retrieved the same validation studies (sheet protocol_history). The check does not show that the records removed by the restriction contain no other relevant studies, and it cannot be used as evidence of the absence of selection bias.
A21: method note | B21: Offline matching of the development titles was used exclusively for threshold selection; all retrieval outcomes were determined from the actual OpenAlex search results.
A22: field check | B22: All 36 indexed validation studies have their primary topic in one of the fields kept (sheet openalex_fields).
A24: Threshold selection on the development set (offline title match)
A25: R | B25: terms in query | C25: development titles matched
A26: 10 | B26: 48 | C26: 1
A27: 20 | B27: 44 | C27: 1
A28: 50 | B28: 36 | C28: 0.977
A29: 100 | B29: 27 | C29: 0.955
A30: 200 | B30: 25 | C30: 0.841
A31: 500 | B31: 21 | C31: 0.727
A32: 1000 | B32: 16 | C32: 0.614
A34: Validation set: per-study result
A35: bibkey | B35: PRISMA category | C35: OpenAlex ID | D35: OpenAlex field | E35: retrieved
A36: assaad2022survey | B36: Causal Identification | C36: W4214698730 | D36: Computer Science | E36: yes
A37: ghazouani2025virtual | B37: Causal Identification | C37: W4413466225 | D37: Economics, Econometrics and Finance | E37: yes
A38: sadeghi2025causal | B38: Causal Identification | C38: W4404439782 | D38: Computer Science | E38: yes
A39: bhalla2025local | B39: Class 1 - Mathematical and System-Dynamics Modelling | C39: W3216173699 | D39: Physics and Astronomy | E39: yes
A40: evangelatos2025modeling | B40: Class 1 - Mathematical and System-Dynamics Modelling | C40: W4412593918 | D40: Social Sciences | E40: yes
A41: huang2025hybrid | B41: Class 2 - Machine & Deep Learning Content Detection | C41: W4413394554 | D41: Social Sciences | E41: yes
A42: mridha2021comprehensive | B42: Class 2 - Machine & Deep Learning Content Detection | C42: W3216370178 | D42: Social Sciences | E42: yes
A43: saadi2025enhancing | B43: Class 2 - Machine & Deep Learning Content Detection | C43: W4411122931 | D43: Social Sciences | E43: yes
A44: sharma2025novel | B44: Class 2 - Machine & Deep Learning Content Detection | C44: W4409256702 | D44: Social Sciences | E44: yes
A45: cui2025toward | B45: Class 3 - Hybrid Human-AI Annotation and Verification | C45: W4415736465 | D45: Social Sciences | E45: yes
A46: hrckova2025autonomation | B46: Class 3 - Hybrid Human-AI Annotation and Verification | C46: W4414032582 | D46: Social Sciences | E46: no
... A69: roy2024unveiling | B69: F5 - Market manipulation and abusive trading detection | C69: W4399205260 | D69: Computer Science | E69: no
A70: cayuela2025influence | B70: Opinion Manipulation: Definition and Typologies | D70: not indexed | E70: not indexed in OpenAlex
A71: ienca2023artificial | B71: Opinion Manipulation: Definition and Typologies | C71: W4381430332 | D71: Social Sciences | E71: yes
A72: kumarsocial | B72: Opinion Manipulation: Definition and Typologies | D72: not indexed | E72: not indexed in OpenAlex
A73: gaillard2021countering | B73: Opinion in Social Networks | C73: W3182204087 | D73: Social Sciences | E73: yes
A75: Additional descriptive count (not part of the protocol; nothing filtered): records of the final query by OpenAlex source type and work type, 20 October 2026 (count_by_source_type.py)
A76: source type (primary location) | B76: records | C76: share
A77: journal | B77: 175350 | C77: 0.56282017
A78: repository | B78: 54218 | C78: 0.17402329
A79: unknown | B79: 27451 | C79: 0.088109361
A80: conference | B80: 25301 | C80: 0.081208515
A81: book series | B81: 14660 | C81: 0.047054141
A82: ebook platform | B82: 14576 | C82: 0.046784527
A84: work type | B84: records | C84: share
A85: article | B85: 186387 | C85: 0.59824558
A86: conference-paper | B86: 52341 | C86: 0.16799869
A87: preprint | B87: 34189 | C87: 0.10973629
A88: book-chapter | B88: 19903 | C88: 0.063882576
A89: other | B89: 6429 | C89: 0.020635135
A90: report | B90: 2663 | C90: 0.00854742
A91: book | B91: 2523 | C91: 0.0080980626
A92: libguides | B92: 1816 | C92: 0.0058288077
A93: review | B93: 1656 | C93: 0.0053152563
A94: conference-abstract | B94: 1135 | C94: 0.0036430048
A95: book-review | B95: 752 | C95: 0.0024136913
A96: reference-entry | B96: 731 | C96: 0.0023462877
... A101: software-paper | B101: 28 | C101: 8.9871484e-05
A103: Included studies 2021-2026 by OpenAlex source type: development set journal 38, repository 2, conference 1, ebook platform 1, book series 1, no source 1; validation set journal 32, repository 2, no source 2, not indexed 2.
A104: A journal-only restriction (not applied) would keep 175,350 records (56.3%) but lose the four retrieved validation studies without a journal source (cui2025toward: no source, huang2025hybrid: no source, fan2024measuring: repository, goldsmith2025causal: repository): validation 25/38 (65.8%). It would also exclude conference papers and preprints, which the review admits.
A105: Work types that the review would not include and that the document-type restriction did not exclude (libguides, software, book reviews, reference entries, supplementary materials, standards, software papers, conference abstracts) account for 5,342 records (1.7%).

Sheet validation_terms
A1: term | B1: kind | C1: source | D1: development titles (of 44) | E1: development categories | F1: OpenAlex title count | G1: over-representation ratio | H1: in frozen query
A2: opinion manipulation | B2: phrase | C2: Table 2 | D2: 1 | E2: Opinion Manipulation: Definition and Typologies | F2: 31 | G2: 52287.12 | H2: no
A3: pump and dump | B3: phrase | C3: Table 2 | D3: 1 | E3: F5 | F3: 80 | G3: 20261.26 | H3: yes
A4: propaganda detection | B4: phrase | C4: Table 2 | D4: 1 | E4: Class 3 | F4: 120 | G4: 13507.51 | H4: no
A5: echo chamber | B5: phrase | C5: development | D5: 2 | E5: Class 4; Class 6 | F5: 354 | G5: 9157.63 | H5: no
A6: influence operations | B6: phrase | C6: Table 2 | D6: 1 | E6: Opinion Manipulation: Definition and Typologies | F6: 213 | G6: 7609.86 | H6: yes
A7: market manipulation | B7: phrase | C7: Table 2 | D7: 1 | E7: F5 | F7: 320 | G7: 5065.32 | H7: no
A8: hawkes process | B8: phrase | C8: development | D8: 2 | E8: Cross-Domain Challenges; F3 | F8: 691 | G8: 4691.46 | H8: no
A9: media sentiment | B9: phrase | C9: development | D9: 2 | E9: Cross-Domain Challenges; F4 | F9: 761 | G9: 4259.92 | H9: no
A10: hawkes | B10: word | C10: development | D10: 3 | E10: Cross-Domain Challenges; F3 | F10: 1145 | G10: 4246.9 | H10: yes
A11: investor attention | B11: phrase | C11: Table 2 | D11: 1 | E11: Causal Identification | F11: 578 | G11: 2804.33 | H11: no
A12: garch model | B12: phrase | C12: development | D12: 2 | E12: F2 | F12: 1401 | G12: 2313.92 | H12: no
A13: stock return | B13: phrase | C13: development | D13: 2 | E13: Cross-Domain Challenges; F1 | F13: 1600 | G13: 2026.13 | H13: no
... A89: modeling | B89: word | C89: development | D89: 2 | E89: Class 1; Class 4 | F89: 2509847 | G89: 1.29 | H89: no
A91: Over-representation ratio = (development titles containing the term / 44) / (OpenAlex title count / N), with the date and document-type restrictions. It measures enrichment of the term in the development set relative to OpenAlex; it is used for query construction and is not an estimate of search precision or specificity. Terms with ratio >= R = 100 were kept; a phrase was dropped when one of its words was itself kept (e.g. "echo chamber" is covered by "echo" and "chamber").

Sheet protocol_history
A1: query | B1: date | C1: restrictions / change | D1: status | E1: records | F1: development set (44) | G1: validation set, all (38) | H1: validation set, indexed (36) | I1: validation studies lost compared with the first configuration
A2: term query without subject-field restriction (rules fixed before any count) | B2: 2026-10-19 | C2: term query; dates 2020-2026; ineligible types excluded | D2: original pre-specified configuration (audit trail) | E2: 528412 | F2: 42/44 = 95.5% (95% CI 84.9%-98.7%) | G2: 29/38 = 76.3% (95% CI 60.8%-87.0%) | H2: 29/36 = 80.6% (95% CI 65.0%-90.2%) | I2: -
A3: + language filter | B3: 2026-10-20 | C3: as above + language:en | D3: dropped (lost two studies without a language) | E3: 427734 | F3: 42/44 = 95.5% (95% CI 84.9%-98.7%) | G3: 27/38 = 71.1% (95% CI 55.2%-83.0%) | H3: 27/36 = 75.0% (95% CI 58.9%-86.2%) | I3: cui2025toward; goldsmith2025causal
A4: + language and subject-field filters | B4: 2026-10-20 | C4: as above + fields of the development studies | D4: dropped (language filter) | E4: 247876 | F4: 42/44 = 95.5% (95% CI 84.9%-98.7%) | G4: 27/38 = 71.1% (95% CI 55.2%-83.0%) | H4: 27/36 = 75.0% (95% CI 58.9%-86.2%) | I4: cui2025toward; goldsmith2025causal
A5: final: + subject-field restriction, no language filter | B5: 2026-10-20 | C5: term query; dates 2020-2026; ineligible types excluded; fields of the development studies | D5: final configuration (reported filtered retrieval result) | E5: 311556 | F5: 42/44 = 95.5% (95% CI 84.9%-98.7%) | G5: 29/38 = 76.3% (95% CI 60.8%-87.0%) | H5: 29/36 = 80.6% (95% CI 65.0%-90.2%) | I5: -
A6: phrases instead of generic terms, K = 50,000 | B6: 2026-10-20 | C6: language:en; every term with > 50,000 title matches replaced by its candidate phrases | D6: rejected (lost validation studies) | E6: 297641 | F6: 39/44 = 88.6% (95% CI 76.0%-95.0%) | G6: 24/38 = 63.2% (95% CI 47.3%-76.6%) | H6: 24/36 = 66.7% (95% CI 50.3%-79.8%) | I6: assaad2022survey; sadeghi2025causal; amieur2025comparative; cui2025toward; goldsmith2025causal
A7: phrases instead of generic terms, K = 10,000 | B7: 2026-10-20 | C7: language:en; every term with > 10,000 title matches replaced by its candidate phrases | D7: rejected (lost validation studies) | E7: 49580 | F7: 26/44 = 59.1% (95% CI 44.4%-72.3%) | G7: 12/38 = 31.6% (95% CI 19.1%-47.5%) | H7: 12/36 = 33.3% (95% CI 20.2%-49.7%) | I7: 17 studies
A9: The term query (27 terms, R = 100) is the same in every row; only the filters change, except in the two rejected rows. Each query was run once. Dated protocol documents with their SHA-256: history/ in the repository (PROTOCOL_v1.md, PROTOCOL_v2.md, PROTOCOL_final_prerun.md and the manifests).
A10: The subject-field restriction was added after the first run, so it was not specified in advance. The field rule (fields of the development studies only) was written before any field data were retrieved; the final configuration was hashed before its run but after the fields of the validation studies were known (show_fields.py), so the restriction is not independently validated.
A11: Language check (20 October 2026): OpenAlex assigns no language to cui2025toward (W4415736465) and goldsmith2025causal (W7106255595), the two validation studies lost with the language filter. The language filter was therefore dropped; the final query retrieves the same validation studies as the first configuration.
A12: Records on 20 October 2026: without the subject-field restriction the query returned 528,902 records (19 October 2026: 528,412; OpenAlex is updated continuously). The reduction by the restriction is computed between the two counts of 20 October 2026.
A13: Records of the first configuration by language (20 October 2026): tagged as English 427,734; not tagged as English (another language or no language assigned) 100,678 (19.1%). Dated 2020: 64,716 (12.2%); with a start date of 2021-01-01 the first configuration would return 463,696 records, with the same validation result.
A14: Confidence intervals are Wilson score intervals.
A16: Records of the query without the subject-field restriction, by OpenAlex field of the primary topic (20 October 2026)
A17: OpenAlex field | B17: records | C17: kept by the field restriction
A18: Social Sciences | B18: 113594 | C18: yes
A19: Computer Science | B19: 96015 | C19: yes
A20: Economics, Econometrics and Finance | B20: 59407 | C20: yes
A21: Business, Management and Accounting | B21: 47166 | C21: no
A22: Medicine | B22: 35127 | C22: no
A23: Engineering | B23: 28389 | C23: no
A24: Decision Sciences | B24: 26014 | C24: yes
A25: Arts and Humanities | B25: 20865 | C25: no
A26: Physics and Astronomy | B26: 16526 | C26: yes
A27: no primary topic | B27: 15218 | C27: no
A28: Psychology | B28: 13711 | C28: no
A29: Environmental Science | B29: 13060 | C29: no
... A44: Veterinary | B44: 355 | C44: no
A45: total | B45: =SUM(B18:B44) -> 528902
A46: kept by the field restriction | B46: =SUMIF(C18:C44,"yes",B18:B44) -> 311556

Sheet openalex_fields
A1: bibkey | B1: set | C1: PRISMA category | D1: OpenAlex ID | E1: field (primary topic) | F1: subfield | G1: primary topic
A2: bellina2025language | B2: development | C2: Class 4 - Network Structure and Propagation Analysis | D2: W4415310342 | E2: Social Sciences | F2: Communication | G2: Social Media and Politics
A3: budak2024misunderstanding | B3: development | C3: Class 5 - Behavioural and Psychological Modelling | D3: W4399366359 | E3: Social Sciences | F3: Sociology and Political Science | G3: Misinformation and Its Impacts
A4: butts2023mathematical | B4: development | C4: Class 1 - Mathematical and System-Dynamics Modelling | D4: W4388048121 | E4: Social Sciences | F4: Sociology and Political Science | G4: Misinformation and Its Impacts
A5: chang2022systematic | B5: development | C5: Opinion Manipulation: Definition and Typologies | D5: W4312651142 | E5: Social Sciences | F5: Sociology and Political Science | G5: Misinformation and Its Impacts
A6: chuai2024did | B6: development | C6: Class 6 - Intervention and Inoculation Strategies | D6: W4404171602 | E6: Social Sciences | F6: Sociology and Political Science | G6: Misinformation and Its Impacts
A7: fan2026skeptik | B7: development | C7: Class 3 - Hybrid Human-AI Annotation and Verification | D7: W4414476222 | E7: Social Sciences | F7: Sociology and Political Science | G7: Misinformation and Its Impacts
A8: govers2025feeds | B8: development | C8: Class 5 - Behavioural and Psychological Modelling | D8: W4408449869 | E8: Social Sciences | F8: Sociology and Political Science | G8: Misinformation and Its Impacts
A9: impicciche2025comparing | B9: development | C9: Class 4 - Network Structure and Propagation Analysis | D9: W4405248842 | E9: Social Sciences | F9: Sociology and Political Science | G9: Misinformation and Its Impacts
A10: khan2024targets | B10: development | C10: Class 5 - Behavioural and Psychological Modelling | D10: W4396218543 | E10: Social Sciences | F10: Sociology and Political Science | G10: Misinformation and Its Impacts
A11: lee2025countering | B11: development | C11: Class 3 - Hybrid Human-AI Annotation and Verification | D11: W4406258040 | E11: Social Sciences | F11: Sociology and Political Science | G11: Misinformation and Its Impacts
A12: loru2026compression | B12: development | C12: Class 4 - Network Structure and Propagation Analysis | D12: W4416841974 | E12: Social Sciences | F12: Sociology and Political Science | G12: Misinformation and Its Impacts
... A79: su2025emotionally | B79: validation | C79: Class 6 - Intervention and Inoculation Strategies | D79: W4415256889 | E79: Computer Science | F79: Artificial Intelligence | G79: Hate Speech and Cyberbullying Detection
A80: cayuela2025influence | B80: validation | C80: Opinion Manipulation: Definition and Typologies | E80: not indexed
A81: kumarsocial | B81: validation | C81: Opinion Manipulation: Definition and Typologies | E81: not indexed
A82: bhalla2025local | B82: validation | C82: Class 1 - Mathematical and System-Dynamics Modelling | D82: W3216173699 | E82: Physics and Astronomy | F82: Statistical and Nonlinear Physics | G82: Opinion Dynamics and Social Influence
A83: la2023doge | B83: validation | C83: F5 - Market manipulation and abusive trading detection | D83: W3159176111 | E83: Decision Sciences | F83: Management Science and Operations Research | G83: Stock Market Forecasting Methods
A85: Studies per field (formulas)
A86: field | B86: development | C86: validation
A87: Social Sciences | B87: =COUNTIFS($E$2:$E$83,A87,$B$2:$B$83,"development") -> 23 | C87: =COUNTIFS($E$2:$E$83,A87,$B$2:$B$83,"validation") -> 21
A88: Economics, Econometrics and Finance | B88: =COUNTIFS($E$2:$E$83,A88,$B$2:$B$83,"development") -> 15 | C88: =COUNTIFS($E$2:$E$83,A88,$B$2:$B$83,"validation") -> 9
A89: Computer Science | B89: =COUNTIFS($E$2:$E$83,A89,$B$2:$B$83,"development") -> 3 | C89: =COUNTIFS($E$2:$E$83,A89,$B$2:$B$83,"validation") -> 4
A90: Physics and Astronomy | B90: =COUNTIFS($E$2:$E$83,A90,$B$2:$B$83,"development") -> 2 | C90: =COUNTIFS($E$2:$E$83,A90,$B$2:$B$83,"validation") -> 1
A91: Decision Sciences | B91: =COUNTIFS($E$2:$E$83,A91,$B$2:$B$83,"development") -> 1 | C91: =COUNTIFS($E$2:$E$83,A91,$B$2:$B$83,"validation") -> 1
A92: not indexed | B92: =COUNTIFS($E$2:$E$83,A92,$B$2:$B$83,"development") -> 0 | C92: =COUNTIFS($E$2:$E$83,A92,$B$2:$B$83,"validation") -> 2
A93: total | B93: =SUM(B87:B92) -> 44 | C93: =SUM(C87:C92) -> 38
A95: OpenAlex field, subfield and topic of each study's primary topic, read with show_fields.py on 20 October 2026 (assigned automatically by OpenAlex). The subject-field restriction keeps the fields of the development studies; every indexed validation study falls in one of them.

Sheet bib_corrections
A1: bibkey | B1: field | C1: old | D1: new | E1: reason | F1: source
A2: chang2022systematic | B2: doi | C2: 10.1016/j.procs.2022.09.374 | D2: 10.1016/j.procs.2022.09.373 | E2: DOI resolved to another article (A reverse personnel assignment method ...) | F2: OpenAlex/Crossref check, verify_corpus.py run 2026-10-19
A3: zhou2020two | B3: doi | C3: 10.1016/j.ins.2020.01.016 | D3: 10.1016/j.ins.2020.01.052 | E3: DOI resolved to another article (Recognizing novel patterns via adversarial learning ...) | F3: OpenAlex/Crossref check, verify_corpus.py run 2026-10-19
A4: mridha2021comprehensive | B4: doi | C4: 10.1109/ACCESS.2021.3128879 | D4: 10.1109/ACCESS.2021.3129329 | E4: DOI resolved to another article (Incremental Attribute Reduction ...) | F4: OpenAlex/Crossref check, verify_corpus.py run 2026-10-19
A5: anderson2003micro | B5: doi | C5: 10.1257/000282803321455214 | D5: 10.1257/000282803321455151 | E5: DOI resolved to another article (Gravity with Gravitas ...) | F5: OpenAlex/Crossref check, verify_corpus.py run 2026-10-19
A6: kogan2023social | B6: doi | C6: 10.1093/rof/rfad010 | D6: 10.1093/rof/rfac058 | E6: DOI resolved to another article (Income, Liquidity, and the Consumption Response ...) | F6: OpenAlex/Crossref check, verify_corpus.py run 2026-10-19
A7: ienca2023artificial | B7: doi | C7: 10.1007/s11245-021-09797-0 | D7: 10.1007/s11245-023-09940-3 | E7: DOI not registered in Crossref; DOI of the matching OpenAlex record | F7: OpenAlex/Crossref check, verify_corpus.py run 2026-10-19
A8: butts2023mathematical | B8: doi | C8: 10.1038/s41598-023-45671-z | D8: 10.1038/s41598-023-45710-2 | E8: DOI not registered in Crossref; DOI of the matching OpenAlex record | F8: OpenAlex/Crossref check, verify_corpus.py run 2026-10-19
A9: smith2024unraveling | B9: doi | C9: 10.1007/s12144-023-04628-2 | D9: 10.1007/s12144-023-05350-1 | E9: DOI not registered in Crossref; DOI of the matching OpenAlex record | F9: OpenAlex/Crossref check, verify_corpus.py run 2026-10-19
A10: budak2024misunderstanding | B10: doi | C10: 10.1038/s41586-024-07328-2 | D10: 10.1038/s41586-024-07417-w | E10: DOI not registered in Crossref; DOI of the matching OpenAlex record | F10: OpenAlex/Crossref check, verify_corpus.py run 2026-10-19
A11: sadeghi2025causal | B11: doi | C11: 10.1007/s41060-024-00679-} | D11: 10.1007/s41060-024-00679-7} | E11: DOI truncated (last character missing) | F11: OpenAlex/Crossref check, verify_corpus.py run 2026-10-19
A12: wang2022causal | B12: doi | C12: year={2022}, | D12: year={2022}, doi={10.1016/j.econlet.2022.110598}, | E12: DOI missing | F12: Full text of the article (Economics Letters 216, 110598)
... A18: stapic2012performing | B18: url | C18: {ttps:// | D18: {https:// | E18: Malformed URL | F18: Manual correction
A19: hausner2012routine | B19: new entry | D19: @article{hausner2012routine, title={Routine development of objectively derived search strategies}, author={Hausner, Elke and Waffenschmidt, Siw and Kaiser, Thomas and Simon, Michael}, journal={Systematic Reviews}, volume={1}, number={1}, pages={19}, year={2012}, doi={10.1186/2046-4053-1-19} } | E19: Method reference for the validated verification search (subsection Reproducibility of the Review) | F19: Systematic Reviews 1:19 (2012); record checked on the University of Southampton repository (eprints.soton.ac.uk/301322)

Sheet decisions_log
A1: date | B1: decision | C1: rationale
A2: 2026-10-18 | B2: Register compiled from the final manuscript and surveybib.bib | C2: Each included work linked to its PRISMA category, section and methodological class.
A3: 2026-10-18 | B3: Corpus membership defined by the PRISMA category boxes | C3: A cited work belongs to the corpus if it is analysed in one of the sections counted in the PRISMA diagram (3.2-3.4, 3.6, 4.1.1, 4.1.2, 4.2, 4.2.1). Works cited only in Sections 1-2 (19) are listed on not_in_corpus.
A4: 2026-10-18 | B4: de2026transformer removed from Class 2 (text and Table C2) | C4: Not counted in the PRISMA diagram (Class 2, n = 8); it reviews text generation rather than manipulation detection.
A5: 2026-10-18 | B5: tong2022assessing, seetharam2024headlines, ghazouani2025virtual restored to Section 4.2.1 | C5: Counted in the PRISMA diagram (Causal Identification, n = 19) but their citations had been lost from the text during revision. Confirmed by the author; descriptions checked against full texts (seetharam, ghazouani) and abstract (tong).
A6: 2026-10-18 | B6: wang2022causal restored to Section 4.2 | C6: Counted in the PRISMA diagram (Cross-Domain Challenges, n = 6) but its citation had been lost from the text. Confirmed by the author; description checked against the full text.
A7: 2026-10-18 | B7: Overlapping studies counted once | C7: Each study is counted in the first PRISMA category where it is analysed; later appearances are recorded in xref_to, reproducing the overlaps shown in the diagram.
A8: 2026-10-18 | B8: CORPUS: 126 studies; all PRISMA category counts and the publication-type composition reproduced | C8: See PRISMA_check and Counts.
A9: 2026-10-19 | B9: Metadata of all 126 studies checked against OpenAlex, and their DOIs against Crossref | C9: verify_corpus.py; 122 of 126 studies indexed in OpenAlex (not indexed: musch2003psychology, cayuela2025influence, kumarsocial; for campbell1997econometrics only a journal item about the book).
A10: 2026-10-19 | B10: 17 corrections applied to surveybib.bib (surveybib_corrected.bib), including 10 DOIs | C10: Five DOIs resolved to other articles, four were not registered in Crossref, one was truncated; see bib_corrections.
A11: 2026-10-19 | B11: Validated verification search: protocol fixed before any OpenAlex count (val/PROTOCOL.md, MANIFEST.txt) | C11: Objective approach (Hausner et al. 2012): stratified random split (seed 20261019) into development (44) and validation (38) sets; terms from development titles (>= 2 titles) and Table 2 keywords; specificity by over-representation relative to OpenAlex; threshold chosen on the development set; one frozen title query run once.
A12: 2026-10-19 | B12: Validated search, result: R = 100, 27 terms, 528,412 records; validation 29/38 (76.3%, 95% CI 60.8-87.0%), 29/36 indexed (80.6%, 95% CI 65.0-90.2%); development 42/44 (95.5%) | C12: Reported as obtained. The query is broad because the corpus spans three domains; the validation studies not retrieved use none of the core terms in their titles (fact-checkers, checkworthiness, emotion, tweets, NFT promotion scams) or, for bradley2024place, were not returned by OpenAlex despite "Reddit" in the title.
... A30: 2026-10-20 | B30: Additional descriptive count: records of the final query by OpenAlex source type and work type (count_by_source_type.py); nothing filtered, protocol and result unchanged | C30: Journal 175,350 (56.3%), repository 54,218, unknown 27,451, conference 25,301, book series 14,660, ebook platform 14,576. A journal-only restriction was considered and not applied: it would lose four retrieved validation studies (cui2025toward, huang2025hybrid without a source; fan2024measuring, goldsmith2025causal in a repository; validation 25/38) and contradict the eligibility criteria (conference papers and preprints are admitted). Ineligible work types not excluded by the document-type restriction account for 5,342 records (1.7%).
